{
  "codigoIBGE": "2700706",
  "municipio": "Batalha",
  "atualizadoEm": "2026-04-22T11:31:19.163Z",
  "totalEstabelecimentos": 13,
  "estabelecimentos": [
    {
      "cnpj": "11376961000111",
      "tipo_combustivel": 1,
      "razao_social": "AUTO POSTO MC LTDA",
      "nome_fantasia": "AUTO POSTO MC",
      "telefone": "",
      "nome_logradouro": "Rua VALDEIR SANTANA SILVA",
      "numero_imovel": "5",
      "bairro": "CENTRO",
      "cep": "57421715",
      "codigo_ibge": "2700706",
      "municipio": "Batalha",
      "latitude": -9.675124,
      "longitude": -37.1326609,
      "valor_minimo": 6.4789,
      "valor_maximo": 7.0802,
      "valor_medio": 6.6332,
      "valor_recente": 6.4797,
      "data_recente": "2026-04-21T22:52:38+00:00"
    },
    {
      "cnpj": "12204558000178",
      "tipo_combustivel": 1,
      "razao_social": "NELSON VIEIRA DA ROCHA LTDA",
      "nome_fantasia": "POSTO BATALHA",
      "telefone": "(82) 99148690",
      "nome_logradouro": "AV GOVERNADOR MUNIZ FALCAO",
      "numero_imovel": "11",
      "bairro": "CENTRO",
      "cep": "57421765",
      "codigo_ibge": "2700706",
      "municipio": "Batalha",
      "latitude": -9.672892,
      "longitude": -37.1357254,
      "valor_minimo": 6.7478,
      "valor_maximo": 7.349,
      "valor_medio": 6.8911,
      "valor_recente": 6.7478,
      "data_recente": "2026-04-22T09:20:55+00:00"
    },
    {
      "cnpj": "15739214000151",
      "tipo_combustivel": 1,
      "razao_social": "AUTO POSTO AUTO PECAS E POUSADA PAGUE MENOS LTDA - EPP",
      "nome_fantasia": "AUTO POSTO PAGUEMENOS",
      "telefone": "(82) 35311131",
      "nome_logradouro": "ROD AL 220",
      "numero_imovel": "1500",
      "bairro": "RODOVIA",
      "cep": "57420000",
      "codigo_ibge": "2700706",
      "municipio": "Batalha",
      "latitude": -9.665694199999999,
      "longitude": -37.1296186,
      "valor_minimo": 6.7961,
      "valor_maximo": 7.15,
      "valor_medio": 6.8203,
      "valor_recente": 6.8009,
      "data_recente": "2026-04-22T09:04:32+00:00"
    },
    {
      "cnpj": "11206098000154",
      "tipo_combustivel": 1,
      "razao_social": "AUTO POSTO POUSADA NOVO HORIZONTE LTDA",
      "nome_fantasia": "",
      "telefone": "(82) 41021750",
      "nome_logradouro": "ROD SENADOR TEOTONIO VILELA (AL - 220)",
      "numero_imovel": "265",
      "bairro": "SAO JOSE",
      "cep": "57420670",
      "codigo_ibge": "2700706",
      "municipio": "Batalha",
      "latitude": -9.674948,
      "longitude": -37.125839,
      "valor_minimo": 5.7499,
      "valor_maximo": 7.35,
      "valor_medio": 7.0698,
      "valor_recente": 7.35,
      "data_recente": "2026-04-22T09:28:18+00:00"
    },
    {
      "cnpj": "12204558000178",
      "tipo_combustivel": 2,
      "razao_social": "NELSON VIEIRA DA ROCHA LTDA",
      "nome_fantasia": "POSTO BATALHA",
      "telefone": "(82) 99148690",
      "nome_logradouro": "AV GOVERNADOR MUNIZ FALCAO",
      "numero_imovel": "11",
      "bairro": "CENTRO",
      "cep": "57421765",
      "codigo_ibge": "2700706",
      "municipio": "Batalha",
      "latitude": -9.672892,
      "longitude": -37.1357254,
      "valor_minimo": 6.8484,
      "valor_maximo": 6.9814,
      "valor_medio": 6.8928,
      "valor_recente": 6.8493,
      "data_recente": "2026-04-21T21:05:59+00:00"
    },
    {
      "cnpj": "11206098000154",
      "tipo_combustivel": 2,
      "razao_social": "AUTO POSTO POUSADA NOVO HORIZONTE LTDA",
      "nome_fantasia": "",
      "telefone": "(82) 41021750",
      "nome_logradouro": "ROD SENADOR TEOTONIO VILELA (AL - 220)",
      "numero_imovel": "265",
      "bairro": "SAO JOSE",
      "cep": "57420670",
      "codigo_ibge": "2700706",
      "municipio": "Batalha",
      "latitude": -9.674948,
      "longitude": -37.125839,
      "valor_minimo": 7.1736,
      "valor_maximo": 7.4499,
      "valor_medio": 7.1974,
      "valor_recente": 7.1798,
      "data_recente": "2026-04-22T08:26:14+00:00"
    },
    {
      "cnpj": "11376961000111",
      "tipo_combustivel": 3,
      "razao_social": "AUTO POSTO MC LTDA",
      "nome_fantasia": "AUTO POSTO MC",
      "telefone": "",
      "nome_logradouro": "Rua VALDEIR SANTANA SILVA",
      "numero_imovel": "5",
      "bairro": "CENTRO",
      "cep": "57421715",
      "codigo_ibge": "2700706",
      "municipio": "Batalha",
      "latitude": -9.675124,
      "longitude": -37.1326609,
      "valor_minimo": 5.2474,
      "valor_maximo": 5.5002,
      "valor_medio": 5.2726,
      "valor_recente": 5.5,
      "data_recente": "2026-04-21T22:52:29+00:00"
    },
    {
      "cnpj": "11206098000154",
      "tipo_combustivel": 3,
      "razao_social": "AUTO POSTO POUSADA NOVO HORIZONTE LTDA",
      "nome_fantasia": "",
      "telefone": "(82) 41021750",
      "nome_logradouro": "ROD SENADOR TEOTONIO VILELA (AL - 220)",
      "numero_imovel": "265",
      "bairro": "SAO JOSE",
      "cep": "57420670",
      "codigo_ibge": "2700706",
      "municipio": "Batalha",
      "latitude": -9.674948,
      "longitude": -37.125839,
      "valor_minimo": 6.1728,
      "valor_maximo": 6.39,
      "valor_medio": 6.2061,
      "valor_recente": 6.1786,
      "data_recente": "2026-04-22T08:17:49+00:00"
    },
    {
      "cnpj": "15739214000151",
      "tipo_combustivel": 4,
      "razao_social": "AUTO POSTO AUTO PECAS E POUSADA PAGUE MENOS LTDA - EPP",
      "nome_fantasia": "AUTO POSTO PAGUEMENOS",
      "telefone": "(82) 35311131",
      "nome_logradouro": "ROD AL 220",
      "numero_imovel": "1500",
      "bairro": "RODOVIA",
      "cep": "57420000",
      "codigo_ibge": "2700706",
      "municipio": "Batalha",
      "latitude": -9.665694199999999,
      "longitude": -37.1296186,
      "valor_minimo": 8.4988,
      "valor_maximo": 8.5011,
      "valor_medio": 8.4999,
      "valor_recente": 8.4992,
      "data_recente": "2026-04-22T08:24:29+00:00"
    },
    {
      "cnpj": "15739214000151",
      "tipo_combustivel": 5,
      "razao_social": "AUTO POSTO AUTO PECAS E POUSADA PAGUE MENOS LTDA - EPP",
      "nome_fantasia": "AUTO POSTO PAGUEMENOS",
      "telefone": "(82) 35311131",
      "nome_logradouro": "ROD AL 220",
      "numero_imovel": "1500",
      "bairro": "RODOVIA",
      "cep": "57420000",
      "codigo_ibge": "2700706",
      "municipio": "Batalha",
      "latitude": -9.665694199999999,
      "longitude": -37.1296186,
      "valor_minimo": 7.2993,
      "valor_maximo": 7.3002,
      "valor_medio": 7.2999,
      "valor_recente": 7.3,
      "data_recente": "2026-04-22T08:57:48+00:00"
    },
    {
      "cnpj": "11376961000111",
      "tipo_combustivel": 5,
      "razao_social": "AUTO POSTO MC LTDA",
      "nome_fantasia": "AUTO POSTO MC",
      "telefone": "",
      "nome_logradouro": "Rua VALDEIR SANTANA SILVA",
      "numero_imovel": "5",
      "bairro": "CENTRO",
      "cep": "57421715",
      "codigo_ibge": "2700706",
      "municipio": "Batalha",
      "latitude": -9.675124,
      "longitude": -37.1326609,
      "valor_minimo": 7.4294,
      "valor_maximo": 7.6503,
      "valor_medio": 7.5692,
      "valor_recente": 7.4301,
      "data_recente": "2026-04-21T21:56:18+00:00"
    },
    {
      "cnpj": "11206098000154",
      "tipo_combustivel": 5,
      "razao_social": "AUTO POSTO POUSADA NOVO HORIZONTE LTDA",
      "nome_fantasia": "",
      "telefone": "(82) 41021750",
      "nome_logradouro": "ROD SENADOR TEOTONIO VILELA (AL - 220)",
      "numero_imovel": "265",
      "bairro": "SAO JOSE",
      "cep": "57420670",
      "codigo_ibge": "2700706",
      "municipio": "Batalha",
      "latitude": -9.674948,
      "longitude": -37.125839,
      "valor_minimo": 7.3998,
      "valor_maximo": 7.99,
      "valor_medio": 7.7181,
      "valor_recente": 7.5896,
      "data_recente": "2026-04-22T09:07:15+00:00"
    },
    {
      "cnpj": "12204558000178",
      "tipo_combustivel": 5,
      "razao_social": "NELSON VIEIRA DA ROCHA LTDA",
      "nome_fantasia": "POSTO BATALHA",
      "telefone": "(82) 99148690",
      "nome_logradouro": "AV GOVERNADOR MUNIZ FALCAO",
      "numero_imovel": "11",
      "bairro": "CENTRO",
      "cep": "57421765",
      "codigo_ibge": "2700706",
      "municipio": "Batalha",
      "latitude": -9.672892,
      "longitude": -37.1357254,
      "valor_minimo": 7.584,
      "valor_maximo": 8.1,
      "valor_medio": 7.6901,
      "valor_recente": 7.69,
      "data_recente": "2026-04-21T21:03:25+00:00"
    }
  ]
}