{
  "data": "2026-04-12",
  "codigoIBGE": "2700300",
  "municipio": "Arapiraca",
  "coletadoEm": "2026-04-12T23:25:28.203Z",
  "vendas": [
    {
      "cnpj": "41702805000164",
      "tipo_combustivel": 1,
      "valor_venda": 5.478007662835249,
      "data_venda": "2026-04-11T17:07:57Z"
    },
    {
      "cnpj": "13564704000139",
      "tipo_combustivel": 1,
      "valor_venda": 5.592105263157895,
      "data_venda": "2026-04-11T18:00:27Z"
    },
    {
      "cnpj": "16527263000193",
      "tipo_combustivel": 1,
      "valor_venda": 5.644986543371748,
      "data_venda": "2026-04-11T16:31:15Z"
    },
    {
      "cnpj": "55862110000154",
      "tipo_combustivel": 1,
      "valor_venda": 6.0606060606060606,
      "data_venda": "2026-04-11T21:07:22Z"
    },
    {
      "cnpj": "39322936000174",
      "tipo_combustivel": 1,
      "valor_venda": 6.48,
      "data_venda": "2026-04-11T20:51:28Z"
    },
    {
      "cnpj": "55894566000104",
      "tipo_combustivel": 1,
      "valor_venda": 6.539445628997868,
      "data_venda": "2026-04-11T20:55:34Z"
    },
    {
      "cnpj": "29763548000175",
      "tipo_combustivel": 1,
      "valor_venda": 6.578947368421052,
      "data_venda": "2026-04-11T21:16:42Z"
    },
    {
      "cnpj": "29945645000189",
      "tipo_combustivel": 1,
      "valor_venda": 6.580184245158865,
      "data_venda": "2026-04-11T20:53:50Z"
    },
    {
      "cnpj": "08738994000150",
      "tipo_combustivel": 1,
      "valor_venda": 6.589930586064494,
      "data_venda": "2026-04-11T21:18:39Z"
    },
    {
      "cnpj": "24083322000100",
      "tipo_combustivel": 1,
      "valor_venda": 6.6,
      "data_venda": "2026-04-11T15:51:43Z"
    },
    {
      "cnpj": "37765274000181",
      "tipo_combustivel": 1,
      "valor_venda": 6.648936170212766,
      "data_venda": "2026-04-11T20:54:57Z"
    },
    {
      "cnpj": "34073062000145",
      "tipo_combustivel": 1,
      "valor_venda": 6.6498204548477196,
      "data_venda": "2026-04-11T21:14:57Z"
    },
    {
      "cnpj": "15007757000184",
      "tipo_combustivel": 1,
      "valor_venda": 6.649951667472209,
      "data_venda": "2026-04-11T14:39:28Z"
    },
    {
      "cnpj": "28256951000145",
      "tipo_combustivel": 1,
      "valor_venda": 6.675567423230975,
      "data_venda": "2026-04-11T21:05:46Z"
    },
    {
      "cnpj": "61812873000193",
      "tipo_combustivel": 1,
      "valor_venda": 6.675567423230975,
      "data_venda": "2026-04-11T21:04:02Z"
    },
    {
      "cnpj": "21309025000141",
      "tipo_combustivel": 1,
      "valor_venda": 6.675567423230975,
      "data_venda": "2026-04-11T21:18:50Z"
    },
    {
      "cnpj": "29736718000122",
      "tipo_combustivel": 1,
      "valor_venda": 6.6776968894771676,
      "data_venda": "2026-04-11T20:22:57Z"
    },
    {
      "cnpj": "37120587000182",
      "tipo_combustivel": 1,
      "valor_venda": 6.67779632721202,
      "data_venda": "2026-04-11T20:58:35Z"
    },
    {
      "cnpj": "54725842000130",
      "tipo_combustivel": 1,
      "valor_venda": 6.67779632721202,
      "data_venda": "2026-04-11T21:14:16Z"
    },
    {
      "cnpj": "29982332000109",
      "tipo_combustivel": 1,
      "valor_venda": 6.678539626001781,
      "data_venda": "2026-04-11T21:18:35Z"
    },
    {
      "cnpj": "23800197000149",
      "tipo_combustivel": 1,
      "valor_venda": 6.67913438418381,
      "data_venda": "2026-04-11T21:14:58Z"
    },
    {
      "cnpj": "07783800000175",
      "tipo_combustivel": 1,
      "valor_venda": 6.679197994987469,
      "data_venda": "2026-04-11T21:12:51Z"
    },
    {
      "cnpj": "30960497000150",
      "tipo_combustivel": 1,
      "valor_venda": 6.679389312977099,
      "data_venda": "2026-04-11T20:42:42Z"
    },
    {
      "cnpj": "17057051000152",
      "tipo_combustivel": 1,
      "valor_venda": 6.679389312977099,
      "data_venda": "2026-04-11T21:12:05Z"
    },
    {
      "cnpj": "57516491000145",
      "tipo_combustivel": 1,
      "valor_venda": 6.679389312977099,
      "data_venda": "2026-04-11T20:46:34Z"
    },
    {
      "cnpj": "25023880000142",
      "tipo_combustivel": 1,
      "valor_venda": 6.679465776293823,
      "data_venda": "2026-04-11T21:16:09Z"
    },
    {
      "cnpj": "13460056000170",
      "tipo_combustivel": 1,
      "valor_venda": 6.679580522343197,
      "data_venda": "2026-04-11T19:41:33Z"
    },
    {
      "cnpj": "17879703000134",
      "tipo_combustivel": 1,
      "valor_venda": 6.679611650485437,
      "data_venda": "2026-04-11T21:08:36Z"
    },
    {
      "cnpj": "28683318000133",
      "tipo_combustivel": 1,
      "valor_venda": 6.679692951849267,
      "data_venda": "2026-04-11T21:08:08Z"
    },
    {
      "cnpj": "34405715000146",
      "tipo_combustivel": 1,
      "valor_venda": 6.6797826494285175,
      "data_venda": "2026-04-11T20:50:32Z"
    },
    {
      "cnpj": "07248398000129",
      "tipo_combustivel": 1,
      "valor_venda": 6.679841897233201,
      "data_venda": "2026-04-11T20:17:02Z"
    },
    {
      "cnpj": "35370972000152",
      "tipo_combustivel": 1,
      "valor_venda": 6.679935880309912,
      "data_venda": "2026-04-11T21:17:21Z"
    },
    {
      "cnpj": "07088557000175",
      "tipo_combustivel": 1,
      "valor_venda": 6.679990007494379,
      "data_venda": "2026-04-11T20:26:56Z"
    },
    {
      "cnpj": "34651149000152",
      "tipo_combustivel": 1,
      "valor_venda": 6.680026720106881,
      "data_venda": "2026-04-11T15:55:48Z"
    },
    {
      "cnpj": "15080185000169",
      "tipo_combustivel": 1,
      "valor_venda": 6.680026720106881,
      "data_venda": "2026-04-11T20:38:18Z"
    },
    {
      "cnpj": "12451076000465",
      "tipo_combustivel": 1,
      "valor_venda": 6.688963210702341,
      "data_venda": "2026-04-11T21:17:44Z"
    },
    {
      "cnpj": "12451076000546",
      "tipo_combustivel": 1,
      "valor_venda": 6.688963210702341,
      "data_venda": "2026-04-11T21:16:45Z"
    },
    {
      "cnpj": "43269122000190",
      "tipo_combustivel": 1,
      "valor_venda": 6.68968589886389,
      "data_venda": "2026-04-11T21:14:29Z"
    },
    {
      "cnpj": "12451076000627",
      "tipo_combustivel": 1,
      "valor_venda": 6.68985817500669,
      "data_venda": "2026-04-11T21:16:52Z"
    },
    {
      "cnpj": "12451076000112",
      "tipo_combustivel": 1,
      "valor_venda": 6.68985817500669,
      "data_venda": "2026-04-11T21:19:43Z"
    },
    {
      "cnpj": "56616166000191",
      "tipo_combustivel": 1,
      "valor_venda": 6.690241804453789,
      "data_venda": "2026-04-11T20:39:30Z"
    },
    {
      "cnpj": "45605930000107",
      "tipo_combustivel": 1,
      "valor_venda": 6.777027027027027,
      "data_venda": "2026-04-11T21:15:48Z"
    },
    {
      "cnpj": "18715178000184",
      "tipo_combustivel": 1,
      "valor_venda": 6.888513513513513,
      "data_venda": "2026-04-11T20:26:18Z"
    },
    {
      "cnpj": "28164941000180",
      "tipo_combustivel": 1,
      "valor_venda": 6.888633754305396,
      "data_venda": "2026-04-11T19:51:07Z"
    },
    {
      "cnpj": "24313645000142",
      "tipo_combustivel": 1,
      "valor_venda": 6.888633754305396,
      "data_venda": "2026-04-11T21:15:39Z"
    },
    {
      "cnpj": "31391653000172",
      "tipo_combustivel": 1,
      "valor_venda": 6.889578855186689,
      "data_venda": "2026-04-11T16:45:27Z"
    },
    {
      "cnpj": "61017230000158",
      "tipo_combustivel": 1,
      "valor_venda": 6.889763779527559,
      "data_venda": "2026-04-11T21:18:25Z"
    },
    {
      "cnpj": "15138057000129",
      "tipo_combustivel": 1,
      "valor_venda": 6.89,
      "data_venda": "2026-04-11T20:14:25Z"
    },
    {
      "cnpj": "29633902000147",
      "tipo_combustivel": 1,
      "valor_venda": 6.978367062107467,
      "data_venda": "2026-04-11T20:55:19Z"
    },
    {
      "cnpj": "02817655000182",
      "tipo_combustivel": 1,
      "valor_venda": 6.978367062107467,
      "data_venda": "2026-04-11T21:18:46Z"
    },
    {
      "cnpj": "35782528000144",
      "tipo_combustivel": 1,
      "valor_venda": 6.978367062107467,
      "data_venda": "2026-04-11T21:12:49Z"
    },
    {
      "cnpj": "29790416000213",
      "tipo_combustivel": 1,
      "valor_venda": 6.978367062107467,
      "data_venda": "2026-04-11T21:05:41Z"
    },
    {
      "cnpj": "29790416000132",
      "tipo_combustivel": 1,
      "valor_venda": 6.978367062107467,
      "data_venda": "2026-04-11T20:59:34Z"
    },
    {
      "cnpj": "29790416000485",
      "tipo_combustivel": 1,
      "valor_venda": 6.979665846392955,
      "data_venda": "2026-04-11T21:16:13Z"
    },
    {
      "cnpj": "29856594000119",
      "tipo_combustivel": 1,
      "valor_venda": 6.9799906933457425,
      "data_venda": "2026-04-11T21:11:49Z"
    },
    {
      "cnpj": "40349483000159",
      "tipo_combustivel": 1,
      "valor_venda": 6.987771400049913,
      "data_venda": "2026-04-11T21:15:15Z"
    },
    {
      "cnpj": "29540082000149",
      "tipo_combustivel": 1,
      "valor_venda": 6.988120195667365,
      "data_venda": "2026-04-11T20:53:45Z"
    },
    {
      "cnpj": "55378874000179",
      "tipo_combustivel": 1,
      "valor_venda": 6.988120195667365,
      "data_venda": "2026-04-11T21:11:51Z"
    },
    {
      "cnpj": "21909741000160",
      "tipo_combustivel": 1,
      "valor_venda": 6.99,
      "data_venda": "2026-04-11T21:18:18Z"
    },
    {
      "cnpj": "25155712000100",
      "tipo_combustivel": 1,
      "valor_venda": 6.990074094785404,
      "data_venda": "2026-04-11T21:16:12Z"
    },
    {
      "cnpj": "01242690000158",
      "tipo_combustivel": 1,
      "valor_venda": 6.990074094785404,
      "data_venda": "2026-04-11T21:13:43Z"
    },
    {
      "cnpj": "40921967000120",
      "tipo_combustivel": 1,
      "valor_venda": 6.990434142752023,
      "data_venda": "2026-04-11T20:43:39Z"
    },
    {
      "cnpj": "01242690000239",
      "tipo_combustivel": 1,
      "valor_venda": 6.990562740300594,
      "data_venda": "2026-04-11T21:10:21Z"
    },
    {
      "cnpj": "08461170000185",
      "tipo_combustivel": 1,
      "valor_venda": 7.089849441476445,
      "data_venda": "2026-04-11T21:18:35Z"
    },
    {
      "cnpj": "33833792000134",
      "tipo_combustivel": 1,
      "valor_venda": 7.189016779919568,
      "data_venda": "2026-04-11T18:50:11Z"
    },
    {
      "cnpj": "12451076000112",
      "tipo_combustivel": 2,
      "valor_venda": 4.906354515050167,
      "data_venda": "2026-04-11T21:02:02Z"
    },
    {
      "cnpj": "16527263000193",
      "tipo_combustivel": 2,
      "valor_venda": 5.477962056051689,
      "data_venda": "2026-04-11T16:32:52Z"
    },
    {
      "cnpj": "13564704000139",
      "tipo_combustivel": 2,
      "valor_venda": 5.592105263157895,
      "data_venda": "2026-04-11T17:30:06Z"
    },
    {
      "cnpj": "41702805000164",
      "tipo_combustivel": 2,
      "valor_venda": 6.026986849628359,
      "data_venda": "2026-04-11T17:05:28Z"
    },
    {
      "cnpj": "29763548000175",
      "tipo_combustivel": 2,
      "valor_venda": 6.578947368421052,
      "data_venda": "2026-04-11T20:46:24Z"
    },
    {
      "cnpj": "29945645000189",
      "tipo_combustivel": 2,
      "valor_venda": 6.579813133307014,
      "data_venda": "2026-04-11T20:02:57Z"
    },
    {
      "cnpj": "08738994000150",
      "tipo_combustivel": 2,
      "valor_venda": 6.589820359281437,
      "data_venda": "2026-04-11T21:20:42Z"
    },
    {
      "cnpj": "37765274000181",
      "tipo_combustivel": 2,
      "valor_venda": 6.648936170212766,
      "data_venda": "2026-04-11T20:54:57Z"
    },
    {
      "cnpj": "55862110000154",
      "tipo_combustivel": 2,
      "valor_venda": 6.6498204548477196,
      "data_venda": "2026-04-11T21:10:48Z"
    },
    {
      "cnpj": "54725842000130",
      "tipo_combustivel": 2,
      "valor_venda": 6.676348547717843,
      "data_venda": "2026-04-11T20:35:05Z"
    },
    {
      "cnpj": "30960497000150",
      "tipo_combustivel": 2,
      "valor_venda": 6.678539626001781,
      "data_venda": "2026-04-11T19:59:01Z"
    },
    {
      "cnpj": "29982332000109",
      "tipo_combustivel": 2,
      "valor_venda": 6.678539626001781,
      "data_venda": "2026-04-11T20:46:55Z"
    },
    {
      "cnpj": "57516491000145",
      "tipo_combustivel": 2,
      "valor_venda": 6.678892964321441,
      "data_venda": "2026-04-11T18:42:40Z"
    },
    {
      "cnpj": "07783800000175",
      "tipo_combustivel": 2,
      "valor_venda": 6.679283090281643,
      "data_venda": "2026-04-11T21:06:28Z"
    },
    {
      "cnpj": "13460056000170",
      "tipo_combustivel": 2,
      "valor_venda": 6.679875333926981,
      "data_venda": "2026-04-11T17:23:59Z"
    },
    {
      "cnpj": "28256951000145",
      "tipo_combustivel": 2,
      "valor_venda": 6.679938350886206,
      "data_venda": "2026-04-11T17:53:42Z"
    },
    {
      "cnpj": "29736718000122",
      "tipo_combustivel": 2,
      "valor_venda": 6.68,
      "data_venda": "2026-04-11T20:22:57Z"
    },
    {
      "cnpj": "33833792000134",
      "tipo_combustivel": 2,
      "valor_venda": 6.68,
      "data_venda": "2026-04-11T19:51:12Z"
    },
    {
      "cnpj": "28683318000133",
      "tipo_combustivel": 2,
      "valor_venda": 6.68,
      "data_venda": "2026-04-11T20:00:50Z"
    },
    {
      "cnpj": "35370972000152",
      "tipo_combustivel": 2,
      "valor_venda": 6.680026720106881,
      "data_venda": "2026-04-11T19:27:41Z"
    },
    {
      "cnpj": "07248398000129",
      "tipo_combustivel": 2,
      "valor_venda": 6.680218608371101,
      "data_venda": "2026-04-11T20:17:02Z"
    },
    {
      "cnpj": "12451076000546",
      "tipo_combustivel": 2,
      "valor_venda": 6.689634052978104,
      "data_venda": "2026-04-11T20:17:59Z"
    },
    {
      "cnpj": "12451076000465",
      "tipo_combustivel": 2,
      "valor_venda": 6.68985817500669,
      "data_venda": "2026-04-11T21:09:52Z"
    },
    {
      "cnpj": "07088557000175",
      "tipo_combustivel": 2,
      "valor_venda": 6.7795232936078005,
      "data_venda": "2026-04-11T20:13:36Z"
    },
    {
      "cnpj": "34651149000152",
      "tipo_combustivel": 2,
      "valor_venda": 6.779661016949152,
      "data_venda": "2026-04-11T15:53:59Z"
    },
    {
      "cnpj": "39322936000174",
      "tipo_combustivel": 2,
      "valor_venda": 6.779661016949152,
      "data_venda": "2026-04-11T20:14:16Z"
    },
    {
      "cnpj": "24083322000100",
      "tipo_combustivel": 2,
      "valor_venda": 6.878048780487805,
      "data_venda": "2026-04-07T01:00:34Z"
    },
    {
      "cnpj": "17057051000152",
      "tipo_combustivel": 2,
      "valor_venda": 6.879944960440317,
      "data_venda": "2026-04-11T20:48:28Z"
    },
    {
      "cnpj": "35782528000144",
      "tipo_combustivel": 2,
      "valor_venda": 6.923076923076923,
      "data_venda": "2026-04-11T20:13:48Z"
    },
    {
      "cnpj": "25023880000142",
      "tipo_combustivel": 2,
      "valor_venda": 6.979166666666667,
      "data_venda": "2026-04-11T20:56:53Z"
    },
    {
      "cnpj": "29790416000132",
      "tipo_combustivel": 2,
      "valor_venda": 6.979500766978107,
      "data_venda": "2026-04-11T21:11:54Z"
    },
    {
      "cnpj": "61812873000193",
      "tipo_combustivel": 2,
      "valor_venda": 6.979584714709475,
      "data_venda": "2026-04-11T21:04:48Z"
    },
    {
      "cnpj": "29790416000485",
      "tipo_combustivel": 2,
      "valor_venda": 6.9796374076240095,
      "data_venda": "2026-04-11T19:53:21Z"
    },
    {
      "cnpj": "29856594000119",
      "tipo_combustivel": 2,
      "valor_venda": 6.980071894740516,
      "data_venda": "2026-04-11T19:04:58Z"
    },
    {
      "cnpj": "45605930000107",
      "tipo_combustivel": 2,
      "valor_venda": 6.989130434782608,
      "data_venda": "2026-04-11T20:23:58Z"
    },
    {
      "cnpj": "21909741000160",
      "tipo_combustivel": 2,
      "valor_venda": 6.991053677932405,
      "data_venda": "2026-04-11T21:01:15Z"
    },
    {
      "cnpj": "24313645000142",
      "tipo_combustivel": 2,
      "valor_venda": 7.089580930411381,
      "data_venda": "2026-04-11T20:53:23Z"
    },
    {
      "cnpj": "08461170000185",
      "tipo_combustivel": 2,
      "valor_venda": 7.08994708994709,
      "data_venda": "2026-04-11T16:58:19Z"
    },
    {
      "cnpj": "56616166000191",
      "tipo_combustivel": 2,
      "valor_venda": 7.139942880456957,
      "data_venda": "2026-04-11T16:57:32Z"
    },
    {
      "cnpj": "02817655000182",
      "tipo_combustivel": 2,
      "valor_venda": 7.1797817346352675,
      "data_venda": "2026-04-11T20:57:31Z"
    },
    {
      "cnpj": "21309025000141",
      "tipo_combustivel": 2,
      "valor_venda": 7.186489399928135,
      "data_venda": "2026-04-11T20:11:18Z"
    },
    {
      "cnpj": "34073062000145",
      "tipo_combustivel": 2,
      "valor_venda": 7.187948350071736,
      "data_venda": "2026-04-11T20:43:30Z"
    },
    {
      "cnpj": "23800197000149",
      "tipo_combustivel": 2,
      "valor_venda": 7.18859820382663,
      "data_venda": "2026-04-11T21:02:05Z"
    },
    {
      "cnpj": "12396339000138",
      "tipo_combustivel": 2,
      "valor_venda": 7.188620607219699,
      "data_venda": "2026-04-11T20:21:26Z"
    },
    {
      "cnpj": "01242690000158",
      "tipo_combustivel": 2,
      "valor_venda": 7.189751801441153,
      "data_venda": "2026-04-11T21:10:44Z"
    },
    {
      "cnpj": "01242690000239",
      "tipo_combustivel": 2,
      "valor_venda": 7.189811010682005,
      "data_venda": "2026-04-11T21:15:32Z"
    },
    {
      "cnpj": "29790416000213",
      "tipo_combustivel": 2,
      "valor_venda": 7.275510204081633,
      "data_venda": "2026-04-11T20:13:48Z"
    },
    {
      "cnpj": "55378874000179",
      "tipo_combustivel": 2,
      "valor_venda": 7.286713286713287,
      "data_venda": "2026-04-11T21:06:36Z"
    },
    {
      "cnpj": "40349483000159",
      "tipo_combustivel": 2,
      "valor_venda": 7.289692374981776,
      "data_venda": "2026-04-11T21:07:55Z"
    },
    {
      "cnpj": "29540082000149",
      "tipo_combustivel": 2,
      "valor_venda": 7.3888331661651625,
      "data_venda": "2026-04-11T17:52:28Z"
    },
    {
      "cnpj": "40921967000120",
      "tipo_combustivel": 2,
      "valor_venda": 7.390470570880661,
      "data_venda": "2026-04-11T19:40:10Z"
    },
    {
      "cnpj": "21909741000160",
      "tipo_combustivel": 2,
      "valor_venda": 8.443908323281061,
      "data_venda": "2026-04-11T20:31:45Z"
    },
    {
      "cnpj": "12451076000112",
      "tipo_combustivel": 3,
      "valor_venda": 3.2336297493936943,
      "data_venda": "2026-04-11T21:05:16Z"
    },
    {
      "cnpj": "41702805000164",
      "tipo_combustivel": 3,
      "valor_venda": 4.041635787913495,
      "data_venda": "2026-04-11T02:46:21Z"
    },
    {
      "cnpj": "16527263000193",
      "tipo_combustivel": 3,
      "valor_venda": 4.141954146132419,
      "data_venda": "2026-04-11T16:32:52Z"
    },
    {
      "cnpj": "13564704000139",
      "tipo_combustivel": 3,
      "valor_venda": 4.490121732189184,
      "data_venda": "2026-04-11T18:00:27Z"
    },
    {
      "cnpj": "28256951000145",
      "tipo_combustivel": 3,
      "valor_venda": 4.742990799937627,
      "data_venda": "2026-04-11T16:01:10Z"
    },
    {
      "cnpj": "29856594000119",
      "tipo_combustivel": 3,
      "valor_venda": 4.9800796812749,
      "data_venda": "2026-04-11T21:13:26Z"
    },
    {
      "cnpj": "29540082000149",
      "tipo_combustivel": 3,
      "valor_venda": 4.986498649864987,
      "data_venda": "2026-04-02T23:26:34Z"
    },
    {
      "cnpj": "34073062000145",
      "tipo_combustivel": 3,
      "valor_venda": 4.988375954832281,
      "data_venda": "2026-04-11T20:52:20Z"
    },
    {
      "cnpj": "55862110000154",
      "tipo_combustivel": 3,
      "valor_venda": 4.988775255674732,
      "data_venda": "2026-04-11T20:49:48Z"
    },
    {
      "cnpj": "37765274000181",
      "tipo_combustivel": 3,
      "valor_venda": 4.989190088142358,
      "data_venda": "2026-04-11T20:06:23Z"
    },
    {
      "cnpj": "54725842000130",
      "tipo_combustivel": 3,
      "valor_venda": 4.98960498960499,
      "data_venda": "2026-04-11T20:21:34Z"
    },
    {
      "cnpj": "33833792000134",
      "tipo_combustivel": 3,
      "valor_venda": 4.989883601913784,
      "data_venda": "2026-04-11T18:02:10Z"
    },
    {
      "cnpj": "15007757000184",
      "tipo_combustivel": 3,
      "valor_venda": 4.989908831512284,
      "data_venda": "2026-04-11T12:51:21Z"
    },
    {
      "cnpj": "35370972000152",
      "tipo_combustivel": 3,
      "valor_venda": 4.990019960079841,
      "data_venda": "2026-04-11T20:27:23Z"
    },
    {
      "cnpj": "21909741000160",
      "tipo_combustivel": 3,
      "valor_venda": 5.053691275167785,
      "data_venda": "2026-04-11T20:00:54Z"
    },
    {
      "cnpj": "12451076000546",
      "tipo_combustivel": 3,
      "valor_venda": 5.089058524173028,
      "data_venda": "2026-04-11T21:10:36Z"
    },
    {
      "cnpj": "29763548000175",
      "tipo_combustivel": 3,
      "valor_venda": 5.089820359281437,
      "data_venda": "2026-04-11T20:18:50Z"
    },
    {
      "cnpj": "29945645000189",
      "tipo_combustivel": 3,
      "valor_venda": 5.089835598310175,
      "data_venda": "2026-04-11T20:02:20Z"
    },
    {
      "cnpj": "61017230000158",
      "tipo_combustivel": 3,
      "valor_venda": 5.0899219545300305,
      "data_venda": "2026-04-11T20:53:48Z"
    },
    {
      "cnpj": "29633902000147",
      "tipo_combustivel": 3,
      "valor_venda": 5.0899219545300305,
      "data_venda": "2026-04-11T21:14:48Z"
    },
    {
      "cnpj": "28683318000133",
      "tipo_combustivel": 3,
      "valor_venda": 5.0899219545300305,
      "data_venda": "2026-04-11T21:08:54Z"
    },
    {
      "cnpj": "25155712000100",
      "tipo_combustivel": 3,
      "valor_venda": 5.139802631578948,
      "data_venda": "2026-04-11T21:16:12Z"
    },
    {
      "cnpj": "17879703000134",
      "tipo_combustivel": 3,
      "valor_venda": 5.1479591836734695,
      "data_venda": "2026-04-11T19:45:34Z"
    },
    {
      "cnpj": "18715178000184",
      "tipo_combustivel": 3,
      "valor_venda": 5.1493305870236865,
      "data_venda": "2026-04-11T19:54:04Z"
    },
    {
      "cnpj": "61812873000193",
      "tipo_combustivel": 3,
      "valor_venda": 5.179558011049724,
      "data_venda": "2026-04-11T19:25:40Z"
    },
    {
      "cnpj": "23800197000149",
      "tipo_combustivel": 3,
      "valor_venda": 5.188067444876784,
      "data_venda": "2026-04-11T21:14:19Z"
    },
    {
      "cnpj": "56616166000191",
      "tipo_combustivel": 3,
      "valor_venda": 5.1894135962636225,
      "data_venda": "2026-04-11T20:40:01Z"
    },
    {
      "cnpj": "31391653000172",
      "tipo_combustivel": 3,
      "valor_venda": 5.189932537623249,
      "data_venda": "2026-04-11T13:15:03Z"
    },
    {
      "cnpj": "39322936000174",
      "tipo_combustivel": 3,
      "valor_venda": 5.189952252439277,
      "data_venda": "2026-04-11T20:32:56Z"
    },
    {
      "cnpj": "25023880000142",
      "tipo_combustivel": 3,
      "valor_venda": 5.189952252439277,
      "data_venda": "2026-04-11T20:49:23Z"
    },
    {
      "cnpj": "28164941000180",
      "tipo_combustivel": 3,
      "valor_venda": 5.285714285714286,
      "data_venda": "2026-04-11T18:53:09Z"
    },
    {
      "cnpj": "08738994000150",
      "tipo_combustivel": 3,
      "valor_venda": 5.287275290800141,
      "data_venda": "2026-04-11T21:04:31Z"
    },
    {
      "cnpj": "57516491000145",
      "tipo_combustivel": 3,
      "valor_venda": 5.289605924358635,
      "data_venda": "2026-04-11T20:27:46Z"
    },
    {
      "cnpj": "40349483000159",
      "tipo_combustivel": 3,
      "valor_venda": 5.289605924358635,
      "data_venda": "2026-04-06T19:17:36Z"
    },
    {
      "cnpj": "01242690000158",
      "tipo_combustivel": 3,
      "valor_venda": 5.289885738468049,
      "data_venda": "2026-04-11T21:09:03Z"
    },
    {
      "cnpj": "02817655000182",
      "tipo_combustivel": 3,
      "valor_venda": 5.379814934366258,
      "data_venda": "2026-04-11T16:22:15Z"
    },
    {
      "cnpj": "07783800000175",
      "tipo_combustivel": 3,
      "valor_venda": 5.3859964093357275,
      "data_venda": "2026-04-11T21:17:39Z"
    },
    {
      "cnpj": "29982332000109",
      "tipo_combustivel": 3,
      "valor_venda": 5.388898868331237,
      "data_venda": "2026-04-11T21:12:34Z"
    },
    {
      "cnpj": "07088557000175",
      "tipo_combustivel": 3,
      "valor_venda": 5.389221556886228,
      "data_venda": "2026-04-11T20:13:36Z"
    },
    {
      "cnpj": "34405715000146",
      "tipo_combustivel": 3,
      "valor_venda": 5.389341115036093,
      "data_venda": "2026-04-11T20:04:03Z"
    },
    {
      "cnpj": "29736718000122",
      "tipo_combustivel": 3,
      "valor_venda": 5.3893829156561575,
      "data_venda": "2026-04-11T20:22:57Z"
    },
    {
      "cnpj": "30960497000150",
      "tipo_combustivel": 3,
      "valor_venda": 5.3893829156561575,
      "data_venda": "2026-04-11T20:09:52Z"
    },
    {
      "cnpj": "34651149000152",
      "tipo_combustivel": 3,
      "valor_venda": 5.3893829156561575,
      "data_venda": "2026-04-11T15:55:48Z"
    },
    {
      "cnpj": "12451076000627",
      "tipo_combustivel": 3,
      "valor_venda": 5.389514943655071,
      "data_venda": "2026-04-11T21:04:51Z"
    },
    {
      "cnpj": "37120587000182",
      "tipo_combustivel": 3,
      "valor_venda": 5.3895754970446,
      "data_venda": "2026-04-11T20:14:43Z"
    },
    {
      "cnpj": "08461170000185",
      "tipo_combustivel": 3,
      "valor_venda": 5.389666307857912,
      "data_venda": "2026-04-11T16:58:19Z"
    },
    {
      "cnpj": "21309025000141",
      "tipo_combustivel": 3,
      "valor_venda": 5.389673385792821,
      "data_venda": "2026-04-11T21:16:14Z"
    },
    {
      "cnpj": "15080185000169",
      "tipo_combustivel": 3,
      "valor_venda": 5.389885807504078,
      "data_venda": "2026-04-11T16:55:19Z"
    },
    {
      "cnpj": "24083322000100",
      "tipo_combustivel": 3,
      "valor_venda": 5.389908256880734,
      "data_venda": "2026-04-11T21:19:25Z"
    },
    {
      "cnpj": "13460056000170",
      "tipo_combustivel": 3,
      "valor_venda": 5.389963887241955,
      "data_venda": "2026-04-11T21:17:05Z"
    },
    {
      "cnpj": "12451076000465",
      "tipo_combustivel": 3,
      "valor_venda": 5.39000539000539,
      "data_venda": "2026-04-11T20:49:58Z"
    },
    {
      "cnpj": "07248398000129",
      "tipo_combustivel": 3,
      "valor_venda": 5.390070921985815,
      "data_venda": "2026-04-11T20:17:02Z"
    },
    {
      "cnpj": "17057051000152",
      "tipo_combustivel": 3,
      "valor_venda": 5.390109149710281,
      "data_venda": "2026-04-11T20:48:14Z"
    },
    {
      "cnpj": "35782528000144",
      "tipo_combustivel": 3,
      "valor_venda": 5.478927203065134,
      "data_venda": "2026-04-11T20:13:48Z"
    },
    {
      "cnpj": "29790416000132",
      "tipo_combustivel": 3,
      "valor_venda": 5.47945205479452,
      "data_venda": "2026-04-11T21:11:54Z"
    },
    {
      "cnpj": "29790416000213",
      "tipo_combustivel": 3,
      "valor_venda": 5.47945205479452,
      "data_venda": "2026-04-11T20:46:00Z"
    },
    {
      "cnpj": "29790416000485",
      "tipo_combustivel": 3,
      "valor_venda": 5.47945205479452,
      "data_venda": "2026-04-11T15:04:51Z"
    },
    {
      "cnpj": "01242690000239",
      "tipo_combustivel": 3,
      "valor_venda": 5.489711934156379,
      "data_venda": "2026-04-11T19:55:05Z"
    },
    {
      "cnpj": "12396339000138",
      "tipo_combustivel": 3,
      "valor_venda": 5.48992673992674,
      "data_venda": "2026-04-11T19:24:04Z"
    },
    {
      "cnpj": "45605930000107",
      "tipo_combustivel": 3,
      "valor_venda": 5.549450549450549,
      "data_venda": "2026-04-11T20:32:31Z"
    },
    {
      "cnpj": "55378874000179",
      "tipo_combustivel": 3,
      "valor_venda": 5.689576695493855,
      "data_venda": "2026-04-11T20:38:17Z"
    },
    {
      "cnpj": "40921967000120",
      "tipo_combustivel": 3,
      "valor_venda": 5.6900065033600695,
      "data_venda": "2026-04-11T16:43:34Z"
    },
    {
      "cnpj": "24313645000142",
      "tipo_combustivel": 3,
      "valor_venda": 5.789717461787864,
      "data_venda": "2026-04-11T21:10:03Z"
    },
    {
      "cnpj": "28256951000145",
      "tipo_combustivel": 4,
      "valor_venda": 6.536780372086893,
      "data_venda": "2026-04-11T15:59:43Z"
    },
    {
      "cnpj": "13460056000170",
      "tipo_combustivel": 4,
      "valor_venda": 7.01073599793041,
      "data_venda": "2026-04-11T15:50:54Z"
    },
    {
      "cnpj": "35370972000152",
      "tipo_combustivel": 4,
      "valor_venda": 7.089988001599787,
      "data_venda": "2026-04-11T21:04:19Z"
    },
    {
      "cnpj": "33833792000134",
      "tipo_combustivel": 4,
      "valor_venda": 7.189845030332653,
      "data_venda": "2026-04-11T16:21:09Z"
    },
    {
      "cnpj": "54725842000130",
      "tipo_combustivel": 4,
      "valor_venda": 7.289964739907294,
      "data_venda": "2026-04-07T20:01:17Z"
    },
    {
      "cnpj": "15138057000129",
      "tipo_combustivel": 4,
      "valor_venda": 7.29,
      "data_venda": "2026-04-11T20:26:48Z"
    },
    {
      "cnpj": "13564704000139",
      "tipo_combustivel": 4,
      "valor_venda": 7.689898349378375,
      "data_venda": "2026-04-11T18:39:18Z"
    },
    {
      "cnpj": "25155712000100",
      "tipo_combustivel": 4,
      "valor_venda": 7.7485832045337455,
      "data_venda": "2026-04-11T13:21:19Z"
    },
    {
      "cnpj": "29763548000175",
      "tipo_combustivel": 4,
      "valor_venda": 7.749535027898326,
      "data_venda": "2026-04-11T17:01:10Z"
    },
    {
      "cnpj": "28683318000133",
      "tipo_combustivel": 4,
      "valor_venda": 7.784663051897754,
      "data_venda": "2026-04-11T15:53:05Z"
    },
    {
      "cnpj": "31391653000172",
      "tipo_combustivel": 4,
      "valor_venda": 8.58857828845824,
      "data_venda": "2026-04-10T23:17:26Z"
    },
    {
      "cnpj": "40921967000120",
      "tipo_combustivel": 5,
      "valor_venda": 3.324963072378139,
      "data_venda": "2026-04-10T18:47:17Z"
    },
    {
      "cnpj": "13460056000170",
      "tipo_combustivel": 5,
      "valor_venda": 6.381000789181525,
      "data_venda": "2026-04-11T15:50:54Z"
    },
    {
      "cnpj": "55862110000154",
      "tipo_combustivel": 5,
      "valor_venda": 6.720766453365745,
      "data_venda": "2026-04-11T20:30:42Z"
    },
    {
      "cnpj": "55862110000154",
      "tipo_combustivel": 5,
      "valor_venda": 6.7585380467345715,
      "data_venda": "2026-04-11T20:24:58Z"
    },
    {
      "cnpj": "28256951000145",
      "tipo_combustivel": 5,
      "valor_venda": 6.88999359931726,
      "data_venda": "2026-04-11T17:27:24Z"
    },
    {
      "cnpj": "21909741000160",
      "tipo_combustivel": 5,
      "valor_venda": 6.93,
      "data_venda": "2026-04-11T20:32:34Z"
    },
    {
      "cnpj": "39322936000174",
      "tipo_combustivel": 5,
      "valor_venda": 6.989748369058714,
      "data_venda": "2026-04-11T21:04:24Z"
    },
    {
      "cnpj": "08461170000185",
      "tipo_combustivel": 5,
      "valor_venda": 6.98998369438621,
      "data_venda": "2026-04-11T21:15:35Z"
    },
    {
      "cnpj": "12451076000112",
      "tipo_combustivel": 5,
      "valor_venda": 6.991672193971553,
      "data_venda": "2026-04-11T20:57:58Z"
    },
    {
      "cnpj": "12451076000627",
      "tipo_combustivel": 5,
      "valor_venda": 7.0107784431137725,
      "data_venda": "2026-04-11T18:31:24Z"
    },
    {
      "cnpj": "34073062000145",
      "tipo_combustivel": 5,
      "valor_venda": 7.0399895679387985,
      "data_venda": "2026-04-11T20:58:41Z"
    },
    {
      "cnpj": "01242690000158",
      "tipo_combustivel": 5,
      "valor_venda": 7.05,
      "data_venda": "2026-04-11T21:11:48Z"
    },
    {
      "cnpj": "07248398000129",
      "tipo_combustivel": 5,
      "valor_venda": 7.089235127478753,
      "data_venda": "2026-04-11T20:17:02Z"
    },
    {
      "cnpj": "15007757000184",
      "tipo_combustivel": 5,
      "valor_venda": 7.089467723669309,
      "data_venda": "2026-04-10T22:10:52Z"
    },
    {
      "cnpj": "13564704000139",
      "tipo_combustivel": 5,
      "valor_venda": 7.089949865483622,
      "data_venda": "2026-04-11T18:25:48Z"
    },
    {
      "cnpj": "56616166000191",
      "tipo_combustivel": 5,
      "valor_venda": 7.089961567642193,
      "data_venda": "2026-04-11T20:18:24Z"
    },
    {
      "cnpj": "29982332000109",
      "tipo_combustivel": 5,
      "valor_venda": 7.09,
      "data_venda": "2026-04-11T21:08:57Z"
    },
    {
      "cnpj": "17057051000152",
      "tipo_combustivel": 5,
      "valor_venda": 7.090028355387524,
      "data_venda": "2026-04-11T17:03:18Z"
    },
    {
      "cnpj": "37765274000181",
      "tipo_combustivel": 5,
      "valor_venda": 7.15000715000715,
      "data_venda": "2026-04-11T20:06:23Z"
    },
    {
      "cnpj": "29633902000147",
      "tipo_combustivel": 5,
      "valor_venda": 7.158989986939487,
      "data_venda": "2026-04-11T16:58:01Z"
    },
    {
      "cnpj": "30960497000150",
      "tipo_combustivel": 5,
      "valor_venda": 7.1797817346352675,
      "data_venda": "2026-04-11T11:41:05Z"
    },
    {
      "cnpj": "29856594000119",
      "tipo_combustivel": 5,
      "valor_venda": 7.1798998569384835,
      "data_venda": "2026-04-11T20:53:35Z"
    },
    {
      "cnpj": "61812873000193",
      "tipo_combustivel": 5,
      "valor_venda": 7.1802236126782235,
      "data_venda": "2026-04-11T19:25:57Z"
    },
    {
      "cnpj": "18715178000184",
      "tipo_combustivel": 5,
      "valor_venda": 7.187948350071736,
      "data_venda": "2026-04-11T18:54:00Z"
    },
    {
      "cnpj": "08738994000150",
      "tipo_combustivel": 5,
      "valor_venda": 7.1890726096333575,
      "data_venda": "2026-04-11T21:17:56Z"
    },
    {
      "cnpj": "21309025000141",
      "tipo_combustivel": 5,
      "valor_venda": 7.1890726096333575,
      "data_venda": "2026-04-11T21:08:43Z"
    },
    {
      "cnpj": "43269122000190",
      "tipo_combustivel": 5,
      "valor_venda": 7.189811010682005,
      "data_venda": "2026-04-11T19:19:35Z"
    },
    {
      "cnpj": "12451076000546",
      "tipo_combustivel": 5,
      "valor_venda": 7.189857165783983,
      "data_venda": "2026-04-11T19:52:36Z"
    },
    {
      "cnpj": "12396339000138",
      "tipo_combustivel": 5,
      "valor_venda": 7.189896472392638,
      "data_venda": "2026-04-11T18:01:09Z"
    },
    {
      "cnpj": "07088557000175",
      "tipo_combustivel": 5,
      "valor_venda": 7.189899629001179,
      "data_venda": "2026-04-11T20:37:18Z"
    },
    {
      "cnpj": "33833792000134",
      "tipo_combustivel": 5,
      "valor_venda": 7.189975803664017,
      "data_venda": "2026-04-11T19:24:17Z"
    },
    {
      "cnpj": "45605930000107",
      "tipo_combustivel": 5,
      "valor_venda": 7.189997736256465,
      "data_venda": "2026-04-11T21:11:35Z"
    },
    {
      "cnpj": "29945645000189",
      "tipo_combustivel": 5,
      "valor_venda": 7.190106413574921,
      "data_venda": "2026-04-11T20:01:46Z"
    },
    {
      "cnpj": "55894566000104",
      "tipo_combustivel": 5,
      "valor_venda": 7.2599997098379445,
      "data_venda": "2026-04-11T17:23:49Z"
    },
    {
      "cnpj": "07783800000175",
      "tipo_combustivel": 5,
      "valor_venda": 7.277676950998185,
      "data_venda": "2026-04-11T21:00:54Z"
    },
    {
      "cnpj": "29790416000485",
      "tipo_combustivel": 5,
      "valor_venda": 7.279079924297569,
      "data_venda": "2026-04-11T16:47:45Z"
    },
    {
      "cnpj": "29790416000132",
      "tipo_combustivel": 5,
      "valor_venda": 7.279337507574227,
      "data_venda": "2026-04-11T20:24:05Z"
    },
    {
      "cnpj": "35782528000144",
      "tipo_combustivel": 5,
      "valor_venda": 7.279609812914027,
      "data_venda": "2026-04-11T20:13:48Z"
    },
    {
      "cnpj": "29790416000213",
      "tipo_combustivel": 5,
      "valor_venda": 7.279812938425565,
      "data_venda": "2026-04-11T20:46:38Z"
    },
    {
      "cnpj": "54725842000130",
      "tipo_combustivel": 5,
      "valor_venda": 7.288629737609329,
      "data_venda": "2026-04-11T16:10:48Z"
    },
    {
      "cnpj": "17879703000134",
      "tipo_combustivel": 5,
      "valor_venda": 7.289879931389366,
      "data_venda": "2026-04-11T19:04:16Z"
    },
    {
      "cnpj": "28683318000133",
      "tipo_combustivel": 5,
      "valor_venda": 7.2899397563074695,
      "data_venda": "2026-04-11T18:26:48Z"
    },
    {
      "cnpj": "34405715000146",
      "tipo_combustivel": 5,
      "valor_venda": 7.289946576007771,
      "data_venda": "2026-04-11T14:46:47Z"
    },
    {
      "cnpj": "29763548000175",
      "tipo_combustivel": 5,
      "valor_venda": 7.2899637545306835,
      "data_venda": "2026-04-11T20:39:53Z"
    },
    {
      "cnpj": "40921967000120",
      "tipo_combustivel": 5,
      "valor_venda": 7.290087463556851,
      "data_venda": "2026-04-11T19:34:28Z"
    },
    {
      "cnpj": "61017230000158",
      "tipo_combustivel": 5,
      "valor_venda": 7.290223809870963,
      "data_venda": "2026-04-11T18:00:40Z"
    },
    {
      "cnpj": "12451076000465",
      "tipo_combustivel": 5,
      "valor_venda": 7.369930738555538,
      "data_venda": "2026-04-11T21:16:24Z"
    },
    {
      "cnpj": "02817655000182",
      "tipo_combustivel": 5,
      "valor_venda": 7.379619949572597,
      "data_venda": "2026-04-11T20:21:59Z"
    },
    {
      "cnpj": "25155712000100",
      "tipo_combustivel": 5,
      "valor_venda": 7.379994036970781,
      "data_venda": "2026-04-11T20:20:15Z"
    },
    {
      "cnpj": "55378874000179",
      "tipo_combustivel": 5,
      "valor_venda": 7.389162561576355,
      "data_venda": "2026-04-11T19:17:38Z"
    },
    {
      "cnpj": "25023880000142",
      "tipo_combustivel": 5,
      "valor_venda": 7.389890629618682,
      "data_venda": "2026-04-11T20:51:28Z"
    },
    {
      "cnpj": "57516491000145",
      "tipo_combustivel": 5,
      "valor_venda": 7.389890629618682,
      "data_venda": "2026-04-10T21:23:39Z"
    },
    {
      "cnpj": "40349483000159",
      "tipo_combustivel": 5,
      "valor_venda": 7.389890629618682,
      "data_venda": "2026-04-11T20:20:04Z"
    },
    {
      "cnpj": "29540082000149",
      "tipo_combustivel": 5,
      "valor_venda": 7.389947586875511,
      "data_venda": "2026-04-11T14:50:20Z"
    },
    {
      "cnpj": "31391653000172",
      "tipo_combustivel": 5,
      "valor_venda": 7.389955686853766,
      "data_venda": "2026-04-10T23:15:54Z"
    },
    {
      "cnpj": "34651149000152",
      "tipo_combustivel": 5,
      "valor_venda": 7.390202702702703,
      "data_venda": "2026-04-10T22:15:55Z"
    },
    {
      "cnpj": "01242690000158",
      "tipo_combustivel": 5,
      "valor_venda": 7.429972509101717,
      "data_venda": "2026-04-11T18:37:39Z"
    },
    {
      "cnpj": "01242690000239",
      "tipo_combustivel": 5,
      "valor_venda": 7.449955713020372,
      "data_venda": "2026-04-11T20:39:17Z"
    },
    {
      "cnpj": "29736718000122",
      "tipo_combustivel": 5,
      "valor_venda": 7.485981308411215,
      "data_venda": "2026-04-11T17:15:02Z"
    },
    {
      "cnpj": "37765274000181",
      "tipo_combustivel": 5,
      "valor_venda": 7.591836734693878,
      "data_venda": "2026-04-11T20:06:23Z"
    },
    {
      "cnpj": "24313645000142",
      "tipo_combustivel": 5,
      "valor_venda": 7.680491551459293,
      "data_venda": "2026-04-11T19:04:45Z"
    },
    {
      "cnpj": "29945645000189",
      "tipo_combustivel": 5,
      "valor_venda": 7.75,
      "data_venda": "2026-04-11T13:33:58Z"
    },
    {
      "cnpj": "01242690000239",
      "tipo_combustivel": 5,
      "valor_venda": 7.84,
      "data_venda": "2026-04-11T20:51:15Z"
    },
    {
      "cnpj": "24083322000100",
      "tipo_combustivel": 5,
      "valor_venda": 7.889546351084813,
      "data_venda": "2026-04-11T19:12:35Z"
    },
    {
      "cnpj": "29982332000109",
      "tipo_combustivel": 5,
      "valor_venda": 7.974481658692185,
      "data_venda": "2026-04-11T20:46:55Z"
    },
    {
      "cnpj": "23800197000149",
      "tipo_combustivel": 5,
      "valor_venda": 8.12981370548351,
      "data_venda": "2026-04-11T20:11:58Z"
    },
    {
      "cnpj": "01242690000158",
      "tipo_combustivel": 6,
      "valor_venda": 4.289863935178107,
      "data_venda": "2026-04-11T20:46:00Z"
    },
    {
      "cnpj": "01242690000239",
      "tipo_combustivel": 6,
      "valor_venda": 4.29000429000429,
      "data_venda": "2026-04-11T21:14:28Z"
    },
    {
      "cnpj": "41702805000164",
      "tipo_combustivel": 1,
      "valor_venda": 5.472747497219133,
      "data_venda": "2026-04-12T02:28:46Z"
    },
    {
      "cnpj": "28256951000145",
      "tipo_combustivel": 1,
      "valor_venda": 5.543980665626101,
      "data_venda": "2026-04-11T23:50:48Z"
    },
    {
      "cnpj": "13564704000139",
      "tipo_combustivel": 1,
      "valor_venda": 5.592105263157895,
      "data_venda": "2026-04-12T00:04:23Z"
    },
    {
      "cnpj": "16527263000193",
      "tipo_combustivel": 1,
      "valor_venda": 5.644970414201183,
      "data_venda": "2026-04-12T02:44:26Z"
    },
    {
      "cnpj": "13460056000170",
      "tipo_combustivel": 1,
      "valor_venda": 6.0119928267204665,
      "data_venda": "2026-04-11T23:32:11Z"
    },
    {
      "cnpj": "55862110000154",
      "tipo_combustivel": 1,
      "valor_venda": 6.117021276595745,
      "data_venda": "2026-04-11T23:02:27Z"
    },
    {
      "cnpj": "12451076000465",
      "tipo_combustivel": 1,
      "valor_venda": 6.522829904666332,
      "data_venda": "2026-04-12T02:42:38Z"
    },
    {
      "cnpj": "12451076000112",
      "tipo_combustivel": 1,
      "valor_venda": 6.523949692266524,
      "data_venda": "2026-04-12T02:44:34Z"
    },
    {
      "cnpj": "55894566000104",
      "tipo_combustivel": 1,
      "valor_venda": 6.539641943734015,
      "data_venda": "2026-04-11T23:33:26Z"
    },
    {
      "cnpj": "29945645000189",
      "tipo_combustivel": 1,
      "valor_venda": 6.578947368421052,
      "data_venda": "2026-04-12T02:29:57Z"
    },
    {
      "cnpj": "29763548000175",
      "tipo_combustivel": 1,
      "valor_venda": 6.579380222383051,
      "data_venda": "2026-04-12T01:04:55Z"
    },
    {
      "cnpj": "08738994000150",
      "tipo_combustivel": 1,
      "valor_venda": 6.589382163087867,
      "data_venda": "2026-04-12T01:04:20Z"
    },
    {
      "cnpj": "34073062000145",
      "tipo_combustivel": 1,
      "valor_venda": 6.644518272425249,
      "data_venda": "2026-04-12T02:31:00Z"
    },
    {
      "cnpj": "15007757000184",
      "tipo_combustivel": 1,
      "valor_venda": 6.648007902535396,
      "data_venda": "2026-04-11T23:48:40Z"
    },
    {
      "cnpj": "37765274000181",
      "tipo_combustivel": 1,
      "valor_venda": 6.648936170212766,
      "data_venda": "2026-04-12T00:16:32Z"
    },
    {
      "cnpj": "08461170000185",
      "tipo_combustivel": 1,
      "valor_venda": 6.648971466489715,
      "data_venda": "2026-04-12T00:37:50Z"
    },
    {
      "cnpj": "54725842000130",
      "tipo_combustivel": 1,
      "valor_venda": 6.675567423230975,
      "data_venda": "2026-04-11T23:02:23Z"
    },
    {
      "cnpj": "30960497000150",
      "tipo_combustivel": 1,
      "valor_venda": 6.675567423230975,
      "data_venda": "2026-04-12T00:57:04Z"
    },
    {
      "cnpj": "07783800000175",
      "tipo_combustivel": 1,
      "valor_venda": 6.675567423230975,
      "data_venda": "2026-04-12T02:35:59Z"
    },
    {
      "cnpj": "34405715000146",
      "tipo_combustivel": 1,
      "valor_venda": 6.677785190126751,
      "data_venda": "2026-04-12T01:19:06Z"
    },
    {
      "cnpj": "39322936000174",
      "tipo_combustivel": 1,
      "valor_venda": 6.67779632721202,
      "data_venda": "2026-04-12T02:24:31Z"
    },
    {
      "cnpj": "28683318000133",
      "tipo_combustivel": 1,
      "valor_venda": 6.678539626001781,
      "data_venda": "2026-04-12T00:00:34Z"
    },
    {
      "cnpj": "34651149000152",
      "tipo_combustivel": 1,
      "valor_venda": 6.678539626001781,
      "data_venda": "2026-04-11T23:01:47Z"
    },
    {
      "cnpj": "57516491000145",
      "tipo_combustivel": 1,
      "valor_venda": 6.67913438418381,
      "data_venda": "2026-04-12T00:08:03Z"
    },
    {
      "cnpj": "17879703000134",
      "tipo_combustivel": 1,
      "valor_venda": 6.679225894845008,
      "data_venda": "2026-04-11T23:39:59Z"
    },
    {
      "cnpj": "29736718000122",
      "tipo_combustivel": 1,
      "valor_venda": 6.679465776293823,
      "data_venda": "2026-04-12T00:49:42Z"
    },
    {
      "cnpj": "37120587000182",
      "tipo_combustivel": 1,
      "valor_venda": 6.679589509692132,
      "data_venda": "2026-04-12T02:24:56Z"
    },
    {
      "cnpj": "29982332000109",
      "tipo_combustivel": 1,
      "valor_venda": 6.6796548844976344,
      "data_venda": "2026-04-12T02:37:27Z"
    },
    {
      "cnpj": "15080185000169",
      "tipo_combustivel": 1,
      "valor_venda": 6.679875333926981,
      "data_venda": "2026-04-12T02:33:59Z"
    },
    {
      "cnpj": "07088557000175",
      "tipo_combustivel": 1,
      "valor_venda": 6.68,
      "data_venda": "2026-04-12T00:14:07Z"
    },
    {
      "cnpj": "29790416000485",
      "tipo_combustivel": 1,
      "valor_venda": 6.68,
      "data_venda": "2026-04-12T00:48:46Z"
    },
    {
      "cnpj": "23800197000149",
      "tipo_combustivel": 1,
      "valor_venda": 6.68,
      "data_venda": "2026-04-12T02:26:45Z"
    },
    {
      "cnpj": "25023880000142",
      "tipo_combustivel": 1,
      "valor_venda": 6.68,
      "data_venda": "2026-04-12T02:07:35Z"
    },
    {
      "cnpj": "21309025000141",
      "tipo_combustivel": 1,
      "valor_venda": 6.68,
      "data_venda": "2026-04-12T02:37:02Z"
    },
    {
      "cnpj": "35370972000152",
      "tipo_combustivel": 1,
      "valor_venda": 6.680026720106881,
      "data_venda": "2026-04-12T01:02:49Z"
    },
    {
      "cnpj": "17057051000152",
      "tipo_combustivel": 1,
      "valor_venda": 6.680026720106881,
      "data_venda": "2026-04-12T02:34:48Z"
    },
    {
      "cnpj": "07248398000129",
      "tipo_combustivel": 1,
      "valor_venda": 6.680718881739517,
      "data_venda": "2026-04-12T00:22:36Z"
    },
    {
      "cnpj": "29856594000119",
      "tipo_combustivel": 1,
      "valor_venda": 6.6815144766147,
      "data_venda": "2026-04-12T00:55:36Z"
    },
    {
      "cnpj": "12451076000546",
      "tipo_combustivel": 1,
      "valor_venda": 6.684491978609626,
      "data_venda": "2026-04-12T02:42:55Z"
    },
    {
      "cnpj": "56616166000191",
      "tipo_combustivel": 1,
      "valor_venda": 6.68985817500669,
      "data_venda": "2026-04-12T00:25:14Z"
    },
    {
      "cnpj": "43269122000190",
      "tipo_combustivel": 1,
      "valor_venda": 6.68985817500669,
      "data_venda": "2026-04-11T23:38:11Z"
    },
    {
      "cnpj": "12451076000627",
      "tipo_combustivel": 1,
      "valor_venda": 6.690026954177897,
      "data_venda": "2026-04-12T01:06:45Z"
    },
    {
      "cnpj": "15138057000129",
      "tipo_combustivel": 1,
      "valor_venda": 6.690282047854565,
      "data_venda": "2026-04-11T23:47:16Z"
    },
    {
      "cnpj": "45605930000107",
      "tipo_combustivel": 1,
      "valor_venda": 6.779661016949152,
      "data_venda": "2026-04-12T02:05:21Z"
    },
    {
      "cnpj": "24313645000142",
      "tipo_combustivel": 1,
      "valor_venda": 6.884008236101579,
      "data_venda": "2026-04-12T02:43:15Z"
    },
    {
      "cnpj": "31391653000172",
      "tipo_combustivel": 1,
      "valor_venda": 6.887778282598819,
      "data_venda": "2026-04-11T23:47:49Z"
    },
    {
      "cnpj": "33833792000134",
      "tipo_combustivel": 1,
      "valor_venda": 6.888950124001102,
      "data_venda": "2026-04-12T01:16:42Z"
    },
    {
      "cnpj": "18715178000184",
      "tipo_combustivel": 1,
      "valor_venda": 6.889763779527559,
      "data_venda": "2026-04-12T00:26:12Z"
    },
    {
      "cnpj": "28164941000180",
      "tipo_combustivel": 1,
      "valor_venda": 6.889899407468651,
      "data_venda": "2026-04-12T00:51:26Z"
    },
    {
      "cnpj": "61017230000158",
      "tipo_combustivel": 1,
      "valor_venda": 6.891798759476223,
      "data_venda": "2026-04-12T00:08:36Z"
    },
    {
      "cnpj": "02817655000182",
      "tipo_combustivel": 1,
      "valor_venda": 6.974965229485396,
      "data_venda": "2026-04-12T00:57:02Z"
    },
    {
      "cnpj": "29633902000147",
      "tipo_combustivel": 1,
      "valor_venda": 6.978367062107467,
      "data_venda": "2026-04-12T01:36:57Z"
    },
    {
      "cnpj": "29790416000132",
      "tipo_combustivel": 1,
      "valor_venda": 6.978367062107467,
      "data_venda": "2026-04-12T00:54:40Z"
    },
    {
      "cnpj": "29790416000213",
      "tipo_combustivel": 1,
      "valor_venda": 6.978367062107467,
      "data_venda": "2026-04-12T00:58:36Z"
    },
    {
      "cnpj": "61812873000193",
      "tipo_combustivel": 1,
      "valor_venda": 6.978367062107467,
      "data_venda": "2026-04-12T00:58:02Z"
    },
    {
      "cnpj": "35782528000144",
      "tipo_combustivel": 1,
      "valor_venda": 6.979291119076065,
      "data_venda": "2026-04-12T00:53:16Z"
    },
    {
      "cnpj": "40349483000159",
      "tipo_combustivel": 1,
      "valor_venda": 6.988120195667365,
      "data_venda": "2026-04-12T01:59:08Z"
    },
    {
      "cnpj": "24083322000100",
      "tipo_combustivel": 1,
      "valor_venda": 6.98909700866648,
      "data_venda": "2026-04-12T01:01:10Z"
    },
    {
      "cnpj": "55378874000179",
      "tipo_combustivel": 1,
      "valor_venda": 6.98909700866648,
      "data_venda": "2026-04-12T01:37:56Z"
    },
    {
      "cnpj": "29540082000149",
      "tipo_combustivel": 1,
      "valor_venda": 6.98909700866648,
      "data_venda": "2026-04-12T01:21:09Z"
    },
    {
      "cnpj": "01242690000158",
      "tipo_combustivel": 1,
      "valor_venda": 6.989748369058714,
      "data_venda": "2026-04-12T02:37:04Z"
    },
    {
      "cnpj": "21909741000160",
      "tipo_combustivel": 1,
      "valor_venda": 6.989748369058714,
      "data_venda": "2026-04-12T00:52:34Z"
    },
    {
      "cnpj": "01242690000239",
      "tipo_combustivel": 1,
      "valor_venda": 6.990111464411754,
      "data_venda": "2026-04-12T02:26:46Z"
    },
    {
      "cnpj": "25155712000100",
      "tipo_combustivel": 1,
      "valor_venda": 6.9906976744186045,
      "data_venda": "2026-04-11T23:18:51Z"
    },
    {
      "cnpj": "40921967000120",
      "tipo_combustivel": 1,
      "valor_venda": 7.189934092270821,
      "data_venda": "2026-04-12T00:53:14Z"
    },
    {
      "cnpj": "16527263000193",
      "tipo_combustivel": 2,
      "valor_venda": 5.477990363474762,
      "data_venda": "2026-04-12T00:01:44Z"
    },
    {
      "cnpj": "28256951000145",
      "tipo_combustivel": 2,
      "valor_venda": 5.477997926506163,
      "data_venda": "2026-04-11T23:46:18Z"
    },
    {
      "cnpj": "13564704000139",
      "tipo_combustivel": 2,
      "valor_venda": 5.592750371808122,
      "data_venda": "2026-04-12T00:04:23Z"
    },
    {
      "cnpj": "13460056000170",
      "tipo_combustivel": 2,
      "valor_venda": 6.011994396778148,
      "data_venda": "2026-04-11T23:31:02Z"
    },
    {
      "cnpj": "41702805000164",
      "tipo_combustivel": 2,
      "valor_venda": 6.110047846889952,
      "data_venda": "2026-04-12T00:34:41Z"
    },
    {
      "cnpj": "12451076000465",
      "tipo_combustivel": 2,
      "valor_venda": 6.523102655237299,
      "data_venda": "2026-04-12T02:42:38Z"
    },
    {
      "cnpj": "55862110000154",
      "tipo_combustivel": 2,
      "valor_venda": 6.557387950525336,
      "data_venda": "2026-04-12T00:04:52Z"
    },
    {
      "cnpj": "29763548000175",
      "tipo_combustivel": 2,
      "valor_venda": 6.578947368421052,
      "data_venda": "2026-04-12T01:04:55Z"
    },
    {
      "cnpj": "29945645000189",
      "tipo_combustivel": 2,
      "valor_venda": 6.579813133307014,
      "data_venda": "2026-04-12T02:10:49Z"
    },
    {
      "cnpj": "08738994000150",
      "tipo_combustivel": 2,
      "valor_venda": 6.589998015479262,
      "data_venda": "2026-04-12T01:02:33Z"
    },
    {
      "cnpj": "37765274000181",
      "tipo_combustivel": 2,
      "valor_venda": 6.650151057401812,
      "data_venda": "2026-04-12T00:16:32Z"
    },
    {
      "cnpj": "54725842000130",
      "tipo_combustivel": 2,
      "valor_venda": 6.67779632721202,
      "data_venda": "2026-04-11T22:52:46Z"
    },
    {
      "cnpj": "57516491000145",
      "tipo_combustivel": 2,
      "valor_venda": 6.678539626001781,
      "data_venda": "2026-04-11T21:58:52Z"
    },
    {
      "cnpj": "29982332000109",
      "tipo_combustivel": 2,
      "valor_venda": 6.6789113374519955,
      "data_venda": "2026-04-12T02:37:27Z"
    },
    {
      "cnpj": "30960497000150",
      "tipo_combustivel": 2,
      "valor_venda": 6.67913438418381,
      "data_venda": "2026-04-12T00:57:04Z"
    },
    {
      "cnpj": "29736718000122",
      "tipo_combustivel": 2,
      "valor_venda": 6.679572763684913,
      "data_venda": "2026-04-12T00:45:14Z"
    },
    {
      "cnpj": "07783800000175",
      "tipo_combustivel": 2,
      "valor_venda": 6.679580522343197,
      "data_venda": "2026-04-12T02:43:33Z"
    },
    {
      "cnpj": "33833792000134",
      "tipo_combustivel": 2,
      "valor_venda": 6.68,
      "data_venda": "2026-04-12T01:14:36Z"
    },
    {
      "cnpj": "28683318000133",
      "tipo_combustivel": 2,
      "valor_venda": 6.68,
      "data_venda": "2026-04-12T00:00:34Z"
    },
    {
      "cnpj": "07248398000129",
      "tipo_combustivel": 2,
      "valor_venda": 6.680010675206832,
      "data_venda": "2026-04-12T01:38:16Z"
    },
    {
      "cnpj": "35370972000152",
      "tipo_combustivel": 2,
      "valor_venda": 6.680026720106881,
      "data_venda": "2026-04-12T00:58:48Z"
    },
    {
      "cnpj": "29856594000119",
      "tipo_combustivel": 2,
      "valor_venda": 6.6815144766147,
      "data_venda": "2026-04-12T00:27:34Z"
    },
    {
      "cnpj": "12451076000546",
      "tipo_combustivel": 2,
      "valor_venda": 6.688963210702341,
      "data_venda": "2026-04-12T00:05:44Z"
    },
    {
      "cnpj": "12451076000112",
      "tipo_combustivel": 2,
      "valor_venda": 6.6901283753873395,
      "data_venda": "2026-04-12T02:15:58Z"
    },
    {
      "cnpj": "07088557000175",
      "tipo_combustivel": 2,
      "valor_venda": 6.779127305443095,
      "data_venda": "2026-04-12T00:14:07Z"
    },
    {
      "cnpj": "34651149000152",
      "tipo_combustivel": 2,
      "valor_venda": 6.779661016949152,
      "data_venda": "2026-04-11T22:32:40Z"
    },
    {
      "cnpj": "17057051000152",
      "tipo_combustivel": 2,
      "valor_venda": 6.879725085910653,
      "data_venda": "2026-04-12T00:51:40Z"
    },
    {
      "cnpj": "29790416000132",
      "tipo_combustivel": 2,
      "valor_venda": 6.978367062107467,
      "data_venda": "2026-04-12T00:21:01Z"
    },
    {
      "cnpj": "39322936000174",
      "tipo_combustivel": 2,
      "valor_venda": 6.979048697621744,
      "data_venda": "2026-04-12T01:16:58Z"
    },
    {
      "cnpj": "35782528000144",
      "tipo_combustivel": 2,
      "valor_venda": 6.979062811565304,
      "data_venda": "2026-04-12T00:53:16Z"
    },
    {
      "cnpj": "29790416000485",
      "tipo_combustivel": 2,
      "valor_venda": 6.98,
      "data_venda": "2026-04-11T23:51:24Z"
    },
    {
      "cnpj": "25023880000142",
      "tipo_combustivel": 2,
      "valor_venda": 6.9800796812749,
      "data_venda": "2026-04-12T00:13:05Z"
    },
    {
      "cnpj": "61812873000193",
      "tipo_combustivel": 2,
      "valor_venda": 6.980474198047419,
      "data_venda": "2026-04-12T00:39:48Z"
    },
    {
      "cnpj": "45605930000107",
      "tipo_combustivel": 2,
      "valor_venda": 6.9865738438587766,
      "data_venda": "2026-04-12T02:10:05Z"
    },
    {
      "cnpj": "12396339000138",
      "tipo_combustivel": 2,
      "valor_venda": 7.086882453151619,
      "data_venda": "2026-04-12T00:37:43Z"
    },
    {
      "cnpj": "08461170000185",
      "tipo_combustivel": 2,
      "valor_venda": 7.089235127478753,
      "data_venda": "2026-04-12T00:53:56Z"
    },
    {
      "cnpj": "24313645000142",
      "tipo_combustivel": 2,
      "valor_venda": 7.089909973108851,
      "data_venda": "2026-04-12T02:21:29Z"
    },
    {
      "cnpj": "56616166000191",
      "tipo_combustivel": 2,
      "valor_venda": 7.140326975476839,
      "data_venda": "2026-04-11T20:23:54Z"
    },
    {
      "cnpj": "02817655000182",
      "tipo_combustivel": 2,
      "valor_venda": 7.176724137931035,
      "data_venda": "2026-04-12T00:17:51Z"
    },
    {
      "cnpj": "34073062000145",
      "tipo_combustivel": 2,
      "valor_venda": 7.18562874251497,
      "data_venda": "2026-04-12T02:34:48Z"
    },
    {
      "cnpj": "01242690000239",
      "tipo_combustivel": 2,
      "valor_venda": 7.1890726096333575,
      "data_venda": "2026-04-12T02:02:45Z"
    },
    {
      "cnpj": "21309025000141",
      "tipo_combustivel": 2,
      "valor_venda": 7.1891891891891895,
      "data_venda": "2026-04-12T00:51:50Z"
    },
    {
      "cnpj": "23800197000149",
      "tipo_combustivel": 2,
      "valor_venda": 7.189542483660131,
      "data_venda": "2026-04-12T02:24:51Z"
    },
    {
      "cnpj": "01242690000158",
      "tipo_combustivel": 2,
      "valor_venda": 7.190106413574921,
      "data_venda": "2026-04-12T02:04:10Z"
    },
    {
      "cnpj": "21909741000160",
      "tipo_combustivel": 2,
      "valor_venda": 7.190647482014389,
      "data_venda": "2026-04-12T00:52:34Z"
    },
    {
      "cnpj": "29790416000213",
      "tipo_combustivel": 2,
      "valor_venda": 7.279609812914027,
      "data_venda": "2026-04-12T00:08:49Z"
    },
    {
      "cnpj": "55378874000179",
      "tipo_combustivel": 2,
      "valor_venda": 7.288629737609329,
      "data_venda": "2026-04-12T01:38:36Z"
    },
    {
      "cnpj": "40349483000159",
      "tipo_combustivel": 2,
      "valor_venda": 7.288629737609329,
      "data_venda": "2026-04-12T02:14:46Z"
    },
    {
      "cnpj": "29540082000149",
      "tipo_combustivel": 2,
      "valor_venda": 7.389162561576355,
      "data_venda": "2026-04-12T01:17:11Z"
    },
    {
      "cnpj": "40921967000120",
      "tipo_combustivel": 2,
      "valor_venda": 7.39,
      "data_venda": "2026-04-11T21:32:24Z"
    },
    {
      "cnpj": "21909741000160",
      "tipo_combustivel": 2,
      "valor_venda": 8.690281562216168,
      "data_venda": "2026-04-12T00:02:13Z"
    },
    {
      "cnpj": "41702805000164",
      "tipo_combustivel": 3,
      "valor_venda": 4.03934249528429,
      "data_venda": "2026-04-12T02:28:46Z"
    },
    {
      "cnpj": "16527263000193",
      "tipo_combustivel": 3,
      "valor_venda": 4.1419625937216775,
      "data_venda": "2026-04-11T23:49:19Z"
    },
    {
      "cnpj": "13564704000139",
      "tipo_combustivel": 3,
      "valor_venda": 4.488933101218603,
      "data_venda": "2026-04-11T23:00:05Z"
    },
    {
      "cnpj": "29633902000147",
      "tipo_combustivel": 3,
      "valor_venda": 4.48900651465798,
      "data_venda": "2026-04-11T23:40:20Z"
    },
    {
      "cnpj": "28256951000145",
      "tipo_combustivel": 3,
      "valor_venda": 4.742921104072545,
      "data_venda": "2026-04-11T23:50:48Z"
    },
    {
      "cnpj": "13460056000170",
      "tipo_combustivel": 3,
      "valor_venda": 4.8509076334025965,
      "data_venda": "2026-04-11T23:31:02Z"
    },
    {
      "cnpj": "54725842000130",
      "tipo_combustivel": 3,
      "valor_venda": 4.987531172069826,
      "data_venda": "2026-04-11T22:23:10Z"
    },
    {
      "cnpj": "34073062000145",
      "tipo_combustivel": 3,
      "valor_venda": 4.988360492184902,
      "data_venda": "2026-04-12T02:09:53Z"
    },
    {
      "cnpj": "15007757000184",
      "tipo_combustivel": 3,
      "valor_venda": 4.989547038327526,
      "data_venda": "2026-04-11T23:11:22Z"
    },
    {
      "cnpj": "37765274000181",
      "tipo_combustivel": 3,
      "valor_venda": 4.98960498960499,
      "data_venda": "2026-04-12T00:16:32Z"
    },
    {
      "cnpj": "33833792000134",
      "tipo_combustivel": 3,
      "valor_venda": 4.989907237304665,
      "data_venda": "2026-04-12T01:17:50Z"
    },
    {
      "cnpj": "35370972000152",
      "tipo_combustivel": 3,
      "valor_venda": 4.9900249376558605,
      "data_venda": "2026-04-12T00:58:48Z"
    },
    {
      "cnpj": "55862110000154",
      "tipo_combustivel": 3,
      "valor_venda": 5.077239958805356,
      "data_venda": "2026-04-12T00:04:52Z"
    },
    {
      "cnpj": "29763548000175",
      "tipo_combustivel": 3,
      "valor_venda": 5.08957654723127,
      "data_venda": "2026-04-12T01:04:55Z"
    },
    {
      "cnpj": "12451076000546",
      "tipo_combustivel": 3,
      "valor_venda": 5.08957654723127,
      "data_venda": "2026-04-12T02:44:06Z"
    },
    {
      "cnpj": "28683318000133",
      "tipo_combustivel": 3,
      "valor_venda": 5.089798589398677,
      "data_venda": "2026-04-12T00:00:34Z"
    },
    {
      "cnpj": "29945645000189",
      "tipo_combustivel": 3,
      "valor_venda": 5.089830508474576,
      "data_venda": "2026-04-12T01:54:53Z"
    },
    {
      "cnpj": "61017230000158",
      "tipo_combustivel": 3,
      "valor_venda": 5.0900946757609695,
      "data_venda": "2026-04-11T22:38:11Z"
    },
    {
      "cnpj": "25155712000100",
      "tipo_combustivel": 3,
      "valor_venda": 5.139773895169578,
      "data_venda": "2026-04-11T23:22:52Z"
    },
    {
      "cnpj": "17879703000134",
      "tipo_combustivel": 3,
      "valor_venda": 5.14967595926345,
      "data_venda": "2026-04-12T02:25:31Z"
    },
    {
      "cnpj": "18715178000184",
      "tipo_combustivel": 3,
      "valor_venda": 5.15,
      "data_venda": "2026-04-11T23:53:54Z"
    },
    {
      "cnpj": "61812873000193",
      "tipo_combustivel": 3,
      "valor_venda": 5.179558011049724,
      "data_venda": "2026-04-12T00:57:12Z"
    },
    {
      "cnpj": "23800197000149",
      "tipo_combustivel": 3,
      "valor_venda": 5.188516084399861,
      "data_venda": "2026-04-12T02:32:14Z"
    },
    {
      "cnpj": "25023880000142",
      "tipo_combustivel": 3,
      "valor_venda": 5.189952252439277,
      "data_venda": "2026-04-12T00:54:46Z"
    },
    {
      "cnpj": "56616166000191",
      "tipo_combustivel": 3,
      "valor_venda": 5.1900869339561435,
      "data_venda": "2026-04-11T21:07:40Z"
    },
    {
      "cnpj": "29856594000119",
      "tipo_combustivel": 3,
      "valor_venda": 5.190311418685121,
      "data_venda": "2026-04-12T00:41:59Z"
    },
    {
      "cnpj": "12451076000112",
      "tipo_combustivel": 3,
      "valor_venda": 5.255498059508409,
      "data_venda": "2026-04-12T02:23:57Z"
    },
    {
      "cnpj": "57516491000145",
      "tipo_combustivel": 3,
      "valor_venda": 5.289139633286319,
      "data_venda": "2026-04-12T00:06:45Z"
    },
    {
      "cnpj": "08738994000150",
      "tipo_combustivel": 3,
      "valor_venda": 5.289885738468049,
      "data_venda": "2026-04-12T01:03:38Z"
    },
    {
      "cnpj": "31391653000172",
      "tipo_combustivel": 3,
      "valor_venda": 5.2899470899470895,
      "data_venda": "2026-04-11T23:47:49Z"
    },
    {
      "cnpj": "02817655000182",
      "tipo_combustivel": 3,
      "valor_venda": 5.379774072081764,
      "data_venda": "2026-04-12T01:00:01Z"
    },
    {
      "cnpj": "08461170000185",
      "tipo_combustivel": 3,
      "valor_venda": 5.38751345532831,
      "data_venda": "2026-04-12T00:09:58Z"
    },
    {
      "cnpj": "21309025000141",
      "tipo_combustivel": 3,
      "valor_venda": 5.389092476826902,
      "data_venda": "2026-04-12T02:22:51Z"
    },
    {
      "cnpj": "29982332000109",
      "tipo_combustivel": 3,
      "valor_venda": 5.389092476826902,
      "data_venda": "2026-04-12T02:37:27Z"
    },
    {
      "cnpj": "29736718000122",
      "tipo_combustivel": 3,
      "valor_venda": 5.389261744966443,
      "data_venda": "2026-04-12T00:53:48Z"
    },
    {
      "cnpj": "12451076000627",
      "tipo_combustivel": 3,
      "valor_venda": 5.3893829156561575,
      "data_venda": "2026-04-12T01:00:16Z"
    },
    {
      "cnpj": "17057051000152",
      "tipo_combustivel": 3,
      "valor_venda": 5.3893829156561575,
      "data_venda": "2026-04-12T02:41:46Z"
    },
    {
      "cnpj": "07783800000175",
      "tipo_combustivel": 3,
      "valor_venda": 5.3893829156561575,
      "data_venda": "2026-04-12T02:32:02Z"
    },
    {
      "cnpj": "07088557000175",
      "tipo_combustivel": 3,
      "valor_venda": 5.389505441224006,
      "data_venda": "2026-04-12T00:14:07Z"
    },
    {
      "cnpj": "24083322000100",
      "tipo_combustivel": 3,
      "valor_venda": 5.389666307857912,
      "data_venda": "2026-04-12T01:01:54Z"
    },
    {
      "cnpj": "30960497000150",
      "tipo_combustivel": 3,
      "valor_venda": 5.389673385792821,
      "data_venda": "2026-04-11T22:23:34Z"
    },
    {
      "cnpj": "34651149000152",
      "tipo_combustivel": 3,
      "valor_venda": 5.389673385792821,
      "data_venda": "2026-04-11T23:01:47Z"
    },
    {
      "cnpj": "39322936000174",
      "tipo_combustivel": 3,
      "valor_venda": 5.389673385792821,
      "data_venda": "2026-04-12T01:21:53Z"
    },
    {
      "cnpj": "34405715000146",
      "tipo_combustivel": 3,
      "valor_venda": 5.389735881468757,
      "data_venda": "2026-04-12T01:13:39Z"
    },
    {
      "cnpj": "15080185000169",
      "tipo_combustivel": 3,
      "valor_venda": 5.389851485148514,
      "data_venda": "2026-04-12T02:33:13Z"
    },
    {
      "cnpj": "37120587000182",
      "tipo_combustivel": 3,
      "valor_venda": 5.389983217030298,
      "data_venda": "2026-04-11T23:57:08Z"
    },
    {
      "cnpj": "07248398000129",
      "tipo_combustivel": 3,
      "valor_venda": 5.390204520990312,
      "data_venda": "2026-04-12T00:22:36Z"
    },
    {
      "cnpj": "21909741000160",
      "tipo_combustivel": 3,
      "valor_venda": 5.39068100358423,
      "data_venda": "2026-04-12T00:02:13Z"
    },
    {
      "cnpj": "35782528000144",
      "tipo_combustivel": 3,
      "valor_venda": 5.478851632697786,
      "data_venda": "2026-04-12T00:53:16Z"
    },
    {
      "cnpj": "29790416000485",
      "tipo_combustivel": 3,
      "valor_venda": 5.47945205479452,
      "data_venda": "2026-04-12T00:39:22Z"
    },
    {
      "cnpj": "29790416000132",
      "tipo_combustivel": 3,
      "valor_venda": 5.47945205479452,
      "data_venda": "2026-04-12T00:46:19Z"
    },
    {
      "cnpj": "29790416000213",
      "tipo_combustivel": 3,
      "valor_venda": 5.47945205479452,
      "data_venda": "2026-04-11T22:03:13Z"
    },
    {
      "cnpj": "12396339000138",
      "tipo_combustivel": 3,
      "valor_venda": 5.489638358390898,
      "data_venda": "2026-04-11T23:43:38Z"
    },
    {
      "cnpj": "01242690000239",
      "tipo_combustivel": 3,
      "valor_venda": 5.490282200505106,
      "data_venda": "2026-04-12T02:29:01Z"
    },
    {
      "cnpj": "45605930000107",
      "tipo_combustivel": 3,
      "valor_venda": 5.5497092218222095,
      "data_venda": "2026-04-12T02:10:05Z"
    },
    {
      "cnpj": "12451076000465",
      "tipo_combustivel": 3,
      "valor_venda": 5.590235721606261,
      "data_venda": "2026-04-12T02:39:26Z"
    },
    {
      "cnpj": "55378874000179",
      "tipo_combustivel": 3,
      "valor_venda": 5.689900426742532,
      "data_venda": "2026-04-12T01:44:45Z"
    },
    {
      "cnpj": "24313645000142",
      "tipo_combustivel": 3,
      "valor_venda": 5.788153579008297,
      "data_venda": "2026-04-12T01:45:29Z"
    },
    {
      "cnpj": "01242690000158",
      "tipo_combustivel": 3,
      "valor_venda": 5.790052689479475,
      "data_venda": "2026-04-12T01:25:00Z"
    },
    {
      "cnpj": "13564704000139",
      "tipo_combustivel": 4,
      "valor_venda": 6.5364503229775455,
      "data_venda": "2026-04-11T23:45:59Z"
    },
    {
      "cnpj": "28256951000145",
      "tipo_combustivel": 4,
      "valor_venda": 6.621662852784135,
      "data_venda": "2026-04-11T23:50:48Z"
    },
    {
      "cnpj": "13460056000170",
      "tipo_combustivel": 4,
      "valor_venda": 6.920859161020614,
      "data_venda": "2026-04-11T23:31:02Z"
    },
    {
      "cnpj": "35370972000152",
      "tipo_combustivel": 4,
      "valor_venda": 7.09,
      "data_venda": "2026-04-12T00:56:37Z"
    },
    {
      "cnpj": "33833792000134",
      "tipo_combustivel": 4,
      "valor_venda": 7.1898925272276335,
      "data_venda": "2026-04-12T01:19:50Z"
    },
    {
      "cnpj": "15138057000129",
      "tipo_combustivel": 4,
      "valor_venda": 7.289864930521815,
      "data_venda": "2026-04-11T22:51:56Z"
    },
    {
      "cnpj": "29763548000175",
      "tipo_combustivel": 4,
      "valor_venda": 7.745933384972889,
      "data_venda": "2026-04-12T00:59:59Z"
    },
    {
      "cnpj": "25155712000100",
      "tipo_combustivel": 4,
      "valor_venda": 7.749535027898326,
      "data_venda": "2026-04-11T22:13:43Z"
    },
    {
      "cnpj": "28683318000133",
      "tipo_combustivel": 4,
      "valor_venda": 7.7899952807928265,
      "data_venda": "2026-04-12T00:00:34Z"
    },
    {
      "cnpj": "31391653000172",
      "tipo_combustivel": 4,
      "valor_venda": 8.589933001202542,
      "data_venda": "2026-04-11T23:13:35Z"
    },
    {
      "cnpj": "28256951000145",
      "tipo_combustivel": 5,
      "valor_venda": 5.924931129476584,
      "data_venda": "2026-04-11T23:46:18Z"
    },
    {
      "cnpj": "13564704000139",
      "tipo_combustivel": 5,
      "valor_venda": 6.026309045869993,
      "data_venda": "2026-04-12T00:06:27Z"
    },
    {
      "cnpj": "13460056000170",
      "tipo_combustivel": 5,
      "valor_venda": 6.471264367816092,
      "data_venda": "2026-04-11T23:31:02Z"
    },
    {
      "cnpj": "39322936000174",
      "tipo_combustivel": 5,
      "valor_venda": 6.7897881586094515,
      "data_venda": "2026-04-11T23:18:51Z"
    },
    {
      "cnpj": "21909741000160",
      "tipo_combustivel": 5,
      "valor_venda": 6.93,
      "data_venda": "2026-04-11T23:46:51Z"
    },
    {
      "cnpj": "34073062000145",
      "tipo_combustivel": 5,
      "valor_venda": 7.089622641509434,
      "data_venda": "2026-04-11T23:39:34Z"
    },
    {
      "cnpj": "15007757000184",
      "tipo_combustivel": 5,
      "valor_venda": 7.089800836345595,
      "data_venda": "2026-04-11T23:12:15Z"
    },
    {
      "cnpj": "07248398000129",
      "tipo_combustivel": 5,
      "valor_venda": 7.090007087172219,
      "data_venda": "2026-04-12T00:22:36Z"
    },
    {
      "cnpj": "56616166000191",
      "tipo_combustivel": 5,
      "valor_venda": 7.090187180941577,
      "data_venda": "2026-04-11T20:04:07Z"
    },
    {
      "cnpj": "17057051000152",
      "tipo_combustivel": 5,
      "valor_venda": 7.090187180941577,
      "data_venda": "2026-04-12T00:59:25Z"
    },
    {
      "cnpj": "25155712000100",
      "tipo_combustivel": 5,
      "valor_venda": 7.130003395329536,
      "data_venda": "2026-04-11T22:59:40Z"
    },
    {
      "cnpj": "30960497000150",
      "tipo_combustivel": 5,
      "valor_venda": 7.142857142857143,
      "data_venda": "2026-04-11T21:40:01Z"
    },
    {
      "cnpj": "07783800000175",
      "tipo_combustivel": 5,
      "valor_venda": 7.144082332761578,
      "data_venda": "2026-04-12T01:06:17Z"
    },
    {
      "cnpj": "55862110000154",
      "tipo_combustivel": 5,
      "valor_venda": 7.149495960534782,
      "data_venda": "2026-04-11T22:53:31Z"
    },
    {
      "cnpj": "37765274000181",
      "tipo_combustivel": 5,
      "valor_venda": 7.150153217568948,
      "data_venda": "2026-04-12T00:18:33Z"
    },
    {
      "cnpj": "29856594000119",
      "tipo_combustivel": 5,
      "valor_venda": 7.179340028694405,
      "data_venda": "2026-04-12T00:26:21Z"
    },
    {
      "cnpj": "12451076000112",
      "tipo_combustivel": 5,
      "valor_venda": 7.186129638500939,
      "data_venda": "2026-04-12T02:44:05Z"
    },
    {
      "cnpj": "21309025000141",
      "tipo_combustivel": 5,
      "valor_venda": 7.1890726096333575,
      "data_venda": "2026-04-12T00:11:58Z"
    },
    {
      "cnpj": "23800197000149",
      "tipo_combustivel": 5,
      "valor_venda": 7.18958947444101,
      "data_venda": "2026-04-12T00:58:39Z"
    },
    {
      "cnpj": "55862110000154",
      "tipo_combustivel": 5,
      "valor_venda": 7.18968924016526,
      "data_venda": "2026-04-11T22:43:42Z"
    },
    {
      "cnpj": "12396339000138",
      "tipo_combustivel": 5,
      "valor_venda": 7.189720766635561,
      "data_venda": "2026-04-11T23:45:56Z"
    },
    {
      "cnpj": "29982332000109",
      "tipo_combustivel": 5,
      "valor_venda": 7.189761779226382,
      "data_venda": "2026-04-12T01:43:58Z"
    },
    {
      "cnpj": "18715178000184",
      "tipo_combustivel": 5,
      "valor_venda": 7.189761779226382,
      "data_venda": "2026-04-11T21:22:15Z"
    },
    {
      "cnpj": "45605930000107",
      "tipo_combustivel": 5,
      "valor_venda": 7.189820359281437,
      "data_venda": "2026-04-12T02:10:05Z"
    },
    {
      "cnpj": "08461170000185",
      "tipo_combustivel": 5,
      "valor_venda": 7.1898230551774684,
      "data_venda": "2026-04-12T00:22:54Z"
    },
    {
      "cnpj": "07088557000175",
      "tipo_combustivel": 5,
      "valor_venda": 7.18988069570217,
      "data_venda": "2026-04-12T00:14:07Z"
    },
    {
      "cnpj": "33833792000134",
      "tipo_combustivel": 5,
      "valor_venda": 7.189899629001179,
      "data_venda": "2026-04-12T01:18:57Z"
    },
    {
      "cnpj": "12451076000546",
      "tipo_combustivel": 5,
      "valor_venda": 7.189914163090129,
      "data_venda": "2026-04-12T00:05:03Z"
    },
    {
      "cnpj": "29945645000189",
      "tipo_combustivel": 5,
      "valor_venda": 7.1899595830674325,
      "data_venda": "2026-04-12T01:43:53Z"
    },
    {
      "cnpj": "08738994000150",
      "tipo_combustivel": 5,
      "valor_venda": 7.19,
      "data_venda": "2026-04-12T01:17:41Z"
    },
    {
      "cnpj": "12451076000627",
      "tipo_combustivel": 5,
      "valor_venda": 7.190106413574921,
      "data_venda": "2026-04-11T22:29:13Z"
    },
    {
      "cnpj": "43269122000190",
      "tipo_combustivel": 5,
      "valor_venda": 7.190106413574921,
      "data_venda": "2026-04-11T23:40:37Z"
    },
    {
      "cnpj": "55894566000104",
      "tipo_combustivel": 5,
      "valor_venda": 7.259965600971267,
      "data_venda": "2026-04-11T22:07:43Z"
    },
    {
      "cnpj": "29790416000132",
      "tipo_combustivel": 5,
      "valor_venda": 7.278391390540923,
      "data_venda": "2026-04-12T00:52:20Z"
    },
    {
      "cnpj": "35782528000144",
      "tipo_combustivel": 5,
      "valor_venda": 7.279874786153679,
      "data_venda": "2026-04-12T00:52:34Z"
    },
    {
      "cnpj": "29790416000213",
      "tipo_combustivel": 5,
      "valor_venda": 7.28,
      "data_venda": "2026-04-11T23:27:30Z"
    },
    {
      "cnpj": "28683318000133",
      "tipo_combustivel": 5,
      "valor_venda": 7.288629737609329,
      "data_venda": "2026-04-12T00:00:34Z"
    },
    {
      "cnpj": "54725842000130",
      "tipo_combustivel": 5,
      "valor_venda": 7.289692374981776,
      "data_venda": "2026-04-11T22:11:43Z"
    },
    {
      "cnpj": "34405715000146",
      "tipo_combustivel": 5,
      "valor_venda": 7.289692374981776,
      "data_venda": "2026-04-11T23:29:36Z"
    },
    {
      "cnpj": "29763548000175",
      "tipo_combustivel": 5,
      "valor_venda": 7.2898550724637685,
      "data_venda": "2026-04-12T01:04:55Z"
    },
    {
      "cnpj": "17879703000134",
      "tipo_combustivel": 5,
      "valor_venda": 7.29,
      "data_venda": "2026-04-11T23:52:55Z"
    },
    {
      "cnpj": "40921967000120",
      "tipo_combustivel": 5,
      "valor_venda": 7.290223809870963,
      "data_venda": "2026-04-12T00:52:54Z"
    },
    {
      "cnpj": "61017230000158",
      "tipo_combustivel": 5,
      "valor_venda": 7.290223809870963,
      "data_venda": "2026-04-11T21:26:09Z"
    },
    {
      "cnpj": "01242690000158",
      "tipo_combustivel": 5,
      "valor_venda": 7.321958969399738,
      "data_venda": "2026-04-12T02:36:54Z"
    },
    {
      "cnpj": "12451076000465",
      "tipo_combustivel": 5,
      "valor_venda": 7.369933677229182,
      "data_venda": "2026-04-12T02:02:27Z"
    },
    {
      "cnpj": "02817655000182",
      "tipo_combustivel": 5,
      "valor_venda": 7.378939277478862,
      "data_venda": "2026-04-12T00:57:02Z"
    },
    {
      "cnpj": "55378874000179",
      "tipo_combustivel": 5,
      "valor_venda": 7.389890629618682,
      "data_venda": "2026-04-12T01:40:06Z"
    },
    {
      "cnpj": "40921967000120",
      "tipo_combustivel": 5,
      "valor_venda": 7.389917038927888,
      "data_venda": "2026-04-11T22:07:37Z"
    },
    {
      "cnpj": "31391653000172",
      "tipo_combustivel": 5,
      "valor_venda": 7.389955686853766,
      "data_venda": "2026-04-11T23:47:49Z"
    },
    {
      "cnpj": "25023880000142",
      "tipo_combustivel": 5,
      "valor_venda": 7.390470570880661,
      "data_venda": "2026-04-12T00:08:23Z"
    },
    {
      "cnpj": "29736718000122",
      "tipo_combustivel": 5,
      "valor_venda": 7.489972959660639,
      "data_venda": "2026-04-11T21:34:26Z"
    },
    {
      "cnpj": "37765274000181",
      "tipo_combustivel": 5,
      "valor_venda": 7.585162755488266,
      "data_venda": "2026-04-11T22:38:56Z"
    },
    {
      "cnpj": "01242690000239",
      "tipo_combustivel": 5,
      "valor_venda": 7.58999288593787,
      "data_venda": "2026-04-12T02:08:23Z"
    },
    {
      "cnpj": "01242690000239",
      "tipo_combustivel": 5,
      "valor_venda": 7.83955223880597,
      "data_venda": "2026-04-12T02:08:23Z"
    },
    {
      "cnpj": "24083322000100",
      "tipo_combustivel": 5,
      "valor_venda": 7.8898575880705355,
      "data_venda": "2026-04-12T01:03:32Z"
    },
    {
      "cnpj": "29982332000109",
      "tipo_combustivel": 5,
      "valor_venda": 7.989773090444231,
      "data_venda": "2026-04-11T21:31:15Z"
    },
    {
      "cnpj": "01242690000158",
      "tipo_combustivel": 5,
      "valor_venda": 7.990028444501262,
      "data_venda": "2026-04-12T02:32:23Z"
    },
    {
      "cnpj": "24313645000142",
      "tipo_combustivel": 5,
      "valor_venda": 8.229806039774122,
      "data_venda": "2026-04-12T01:38:25Z"
    },
    {
      "cnpj": "01242690000158",
      "tipo_combustivel": 6,
      "valor_venda": 4.289957917319911,
      "data_venda": "2026-04-12T02:34:52Z"
    },
    {
      "cnpj": "01242690000239",
      "tipo_combustivel": 6,
      "valor_venda": 4.29002803939895,
      "data_venda": "2026-04-12T02:27:32Z"
    }
  ]
}