{
  "data": "2026-04-12",
  "codigoIBGE": "2704807",
  "municipio": "Maribondo",
  "coletadoEm": "2026-04-12T09:56:44.721Z",
  "vendas": [
    {
      "cnpj": "05408092000167",
      "tipo_combustivel": 1,
      "valor_venda": 6.550060720550533,
      "data_venda": "2026-04-11T21:17:21Z"
    },
    {
      "cnpj": "05408092000400",
      "tipo_combustivel": 1,
      "valor_venda": 6.589960915199157,
      "data_venda": "2026-04-11T20:52:31Z"
    },
    {
      "cnpj": "24466310000164",
      "tipo_combustivel": 1,
      "valor_venda": 6.889194769442533,
      "data_venda": "2026-04-11T21:18:16Z"
    },
    {
      "cnpj": "06964197000165",
      "tipo_combustivel": 1,
      "valor_venda": 6.97997443544951,
      "data_venda": "2026-04-11T21:18:17Z"
    },
    {
      "cnpj": "05408092000167",
      "tipo_combustivel": 3,
      "valor_venda": 4.989965829581819,
      "data_venda": "2026-04-11T20:48:30Z"
    },
    {
      "cnpj": "05408092000400",
      "tipo_combustivel": 3,
      "valor_venda": 5.0899219545300305,
      "data_venda": "2026-04-11T21:12:49Z"
    },
    {
      "cnpj": "05408092000167",
      "tipo_combustivel": 4,
      "valor_venda": 7.0900971149074925,
      "data_venda": "2026-04-11T20:48:01Z"
    },
    {
      "cnpj": "05408092000400",
      "tipo_combustivel": 5,
      "valor_venda": 7.089726484322882,
      "data_venda": "2026-04-11T17:13:57Z"
    },
    {
      "cnpj": "24466310000164",
      "tipo_combustivel": 5,
      "valor_venda": 7.289692374981776,
      "data_venda": "2026-04-11T21:15:42Z"
    },
    {
      "cnpj": "06964197000165",
      "tipo_combustivel": 5,
      "valor_venda": 7.289974511469839,
      "data_venda": "2026-04-11T21:15:30Z"
    },
    {
      "cnpj": "05408092000167",
      "tipo_combustivel": 1,
      "valor_venda": 6.549646319098769,
      "data_venda": "2026-04-12T02:40:45Z"
    },
    {
      "cnpj": "05408092000400",
      "tipo_combustivel": 1,
      "valor_venda": 6.59098387627509,
      "data_venda": "2026-04-12T02:39:47Z"
    },
    {
      "cnpj": "24466310000164",
      "tipo_combustivel": 1,
      "valor_venda": 6.889899407468651,
      "data_venda": "2026-04-11T23:37:45Z"
    },
    {
      "cnpj": "06964197000165",
      "tipo_combustivel": 1,
      "valor_venda": 6.890215893431328,
      "data_venda": "2026-04-11T23:48:44Z"
    },
    {
      "cnpj": "05408092000167",
      "tipo_combustivel": 3,
      "valor_venda": 4.9897330595482545,
      "data_venda": "2026-04-11T23:22:48Z"
    },
    {
      "cnpj": "05408092000400",
      "tipo_combustivel": 3,
      "valor_venda": 5.0902389425521095,
      "data_venda": "2026-04-12T02:30:26Z"
    },
    {
      "cnpj": "05408092000167",
      "tipo_combustivel": 4,
      "valor_venda": 7.090007087172219,
      "data_venda": "2026-04-11T22:09:21Z"
    },
    {
      "cnpj": "05408092000400",
      "tipo_combustivel": 5,
      "valor_venda": 7.090007087172219,
      "data_venda": "2026-04-12T01:13:49Z"
    },
    {
      "cnpj": "24466310000164",
      "tipo_combustivel": 5,
      "valor_venda": 7.289665211062591,
      "data_venda": "2026-04-11T23:26:45Z"
    },
    {
      "cnpj": "06964197000165",
      "tipo_combustivel": 5,
      "valor_venda": 7.289692374981776,
      "data_venda": "2026-04-11T23:18:10Z"
    }
  ]
}