{
  "data": "2026-04-12",
  "codigoIBGE": "2704609",
  "municipio": "Maravilha",
  "coletadoEm": "2026-04-12T08:22:49.673Z",
  "vendas": [
    {
      "cnpj": "60501647000129",
      "tipo_combustivel": 1,
      "valor_venda": 6.7697931828182645,
      "data_venda": "2026-04-11T21:17:24Z"
    },
    {
      "cnpj": "08418303000564",
      "tipo_combustivel": 2,
      "valor_venda": 5.455886445866963,
      "data_venda": "2026-04-11T21:07:55Z"
    },
    {
      "cnpj": "14683196000251",
      "tipo_combustivel": 2,
      "valor_venda": 6.757664846703066,
      "data_venda": "2026-04-11T20:20:22Z"
    },
    {
      "cnpj": "60501647000129",
      "tipo_combustivel": 2,
      "valor_venda": 6.7897881586094515,
      "data_venda": "2026-04-11T21:07:37Z"
    },
    {
      "cnpj": "08418303000564",
      "tipo_combustivel": 3,
      "valor_venda": 5.529801324503311,
      "data_venda": "2026-04-11T21:04:21Z"
    },
    {
      "cnpj": "60501647000129",
      "tipo_combustivel": 3,
      "valor_venda": 5.619871866921434,
      "data_venda": "2026-04-11T21:09:06Z"
    },
    {
      "cnpj": "08418303000564",
      "tipo_combustivel": 5,
      "valor_venda": 5.831149927219796,
      "data_venda": "2026-04-11T20:54:52Z"
    },
    {
      "cnpj": "60501647000129",
      "tipo_combustivel": 5,
      "valor_venda": 7.299980533385244,
      "data_venda": "2026-04-11T21:13:13Z"
    },
    {
      "cnpj": "60501647000129",
      "tipo_combustivel": 1,
      "valor_venda": 6.769564040075819,
      "data_venda": "2026-04-12T01:12:34Z"
    },
    {
      "cnpj": "14683196000251",
      "tipo_combustivel": 2,
      "valor_venda": 6.758389261744966,
      "data_venda": "2026-04-11T23:53:54Z"
    },
    {
      "cnpj": "60501647000129",
      "tipo_combustivel": 2,
      "valor_venda": 6.788866259334691,
      "data_venda": "2026-04-12T00:43:22Z"
    },
    {
      "cnpj": "60501647000129",
      "tipo_combustivel": 3,
      "valor_venda": 5.619950825430277,
      "data_venda": "2026-04-11T23:08:57Z"
    },
    {
      "cnpj": "60501647000129",
      "tipo_combustivel": 5,
      "valor_venda": 7.299802905321556,
      "data_venda": "2026-04-11T23:08:57Z"
    }
  ]
}