{
  "data": "2026-04-14",
  "codigoIBGE": "2708006",
  "municipio": "Santana do Ipanema",
  "coletadoEm": "2026-04-14T08:57:54.846Z",
  "vendas": [
    {
      "cnpj": "08418303000130",
      "tipo_combustivel": 1,
      "valor_venda": 6.639700883752549,
      "data_venda": "2026-04-13T20:41:15Z"
    },
    {
      "cnpj": "04979169000196",
      "tipo_combustivel": 1,
      "valor_venda": 6.9100346020761245,
      "data_venda": "2026-04-13T20:48:26Z"
    },
    {
      "cnpj": "05885727000117",
      "tipo_combustivel": 1,
      "valor_venda": 6.93000693000693,
      "data_venda": "2026-04-13T20:30:48Z"
    },
    {
      "cnpj": "12688818000128",
      "tipo_combustivel": 1,
      "valor_venda": 6.939625260235947,
      "data_venda": "2026-04-13T20:02:21Z"
    },
    {
      "cnpj": "26362482000113",
      "tipo_combustivel": 1,
      "valor_venda": 6.948976049982645,
      "data_venda": "2026-04-13T20:41:44Z"
    },
    {
      "cnpj": "08529008000151",
      "tipo_combustivel": 1,
      "valor_venda": 6.950236308034473,
      "data_venda": "2026-04-13T20:17:21Z"
    },
    {
      "cnpj": "08529008000232",
      "tipo_combustivel": 1,
      "valor_venda": 6.950292397660819,
      "data_venda": "2026-04-13T20:48:11Z"
    },
    {
      "cnpj": "01332922000169",
      "tipo_combustivel": 1,
      "valor_venda": 6.980024459845088,
      "data_venda": "2026-04-13T20:44:20Z"
    },
    {
      "cnpj": "05738409000123",
      "tipo_combustivel": 2,
      "valor_venda": 6.699933020763563,
      "data_venda": "2026-04-13T19:59:44Z"
    },
    {
      "cnpj": "26362482000113",
      "tipo_combustivel": 2,
      "valor_venda": 7.050055393292376,
      "data_venda": "2026-04-13T20:34:20Z"
    },
    {
      "cnpj": "08529008000151",
      "tipo_combustivel": 2,
      "valor_venda": 7.050197405527355,
      "data_venda": "2026-04-13T19:52:18Z"
    },
    {
      "cnpj": "08529008000232",
      "tipo_combustivel": 2,
      "valor_venda": 7.090522335145356,
      "data_venda": "2026-04-13T20:41:05Z"
    },
    {
      "cnpj": "01332922000169",
      "tipo_combustivel": 2,
      "valor_venda": 7.139933365064255,
      "data_venda": "2026-04-13T07:27:47Z"
    },
    {
      "cnpj": "05885727000117",
      "tipo_combustivel": 2,
      "valor_venda": 7.142857142857143,
      "data_venda": "2026-04-13T15:22:57Z"
    },
    {
      "cnpj": "08418303000130",
      "tipo_combustivel": 2,
      "valor_venda": 7.45,
      "data_venda": "2026-04-13T19:57:59Z"
    },
    {
      "cnpj": "05738409000123",
      "tipo_combustivel": 3,
      "valor_venda": 5.3002114164904865,
      "data_venda": "2026-04-13T19:29:43Z"
    },
    {
      "cnpj": "12688818000128",
      "tipo_combustivel": 3,
      "valor_venda": 5.600044800358403,
      "data_venda": "2026-04-13T19:56:00Z"
    },
    {
      "cnpj": "05885727000117",
      "tipo_combustivel": 3,
      "valor_venda": 5.928853754940712,
      "data_venda": "2026-04-13T15:23:52Z"
    },
    {
      "cnpj": "04979169000196",
      "tipo_combustivel": 3,
      "valor_venda": 5.930011862396204,
      "data_venda": "2026-04-13T20:42:14Z"
    },
    {
      "cnpj": "08529008000232",
      "tipo_combustivel": 3,
      "valor_venda": 5.950019833399445,
      "data_venda": "2026-04-13T19:08:45Z"
    },
    {
      "cnpj": "26362482000113",
      "tipo_combustivel": 3,
      "valor_venda": 5.958579881656805,
      "data_venda": "2026-04-13T19:59:52Z"
    },
    {
      "cnpj": "08418303000130",
      "tipo_combustivel": 3,
      "valor_venda": 5.960071513706794,
      "data_venda": "2026-04-13T20:42:58Z"
    },
    {
      "cnpj": "08529008000151",
      "tipo_combustivel": 3,
      "valor_venda": 5.960185957801883,
      "data_venda": "2026-04-13T19:35:52Z"
    },
    {
      "cnpj": "01332922000169",
      "tipo_combustivel": 3,
      "valor_venda": 5.969828871265876,
      "data_venda": "2026-04-13T07:27:47Z"
    },
    {
      "cnpj": "05738409000123",
      "tipo_combustivel": 5,
      "valor_venda": 7.5,
      "data_venda": "2026-04-13T18:25:44Z"
    },
    {
      "cnpj": "12688818000128",
      "tipo_combustivel": 5,
      "valor_venda": 7.799703611262772,
      "data_venda": "2026-04-13T19:56:00Z"
    },
    {
      "cnpj": "04979169000196",
      "tipo_combustivel": 5,
      "valor_venda": 7.800312012480499,
      "data_venda": "2026-04-13T20:42:52Z"
    },
    {
      "cnpj": "05885727000117",
      "tipo_combustivel": 5,
      "valor_venda": 7.830036018165684,
      "data_venda": "2026-04-13T15:24:00Z"
    },
    {
      "cnpj": "08529008000151",
      "tipo_combustivel": 5,
      "valor_venda": 7.849909726038151,
      "data_venda": "2026-04-13T19:16:37Z"
    },
    {
      "cnpj": "08529008000232",
      "tipo_combustivel": 5,
      "valor_venda": 7.849909726038151,
      "data_venda": "2026-04-13T20:47:49Z"
    },
    {
      "cnpj": "08418303000130",
      "tipo_combustivel": 5,
      "valor_venda": 7.8499369482976045,
      "data_venda": "2026-04-13T20:42:58Z"
    },
    {
      "cnpj": "08529008000151",
      "tipo_combustivel": 5,
      "valor_venda": 7.85011513502198,
      "data_venda": "2026-04-13T19:27:29Z"
    },
    {
      "cnpj": "26362482000113",
      "tipo_combustivel": 5,
      "valor_venda": 7.850196078431373,
      "data_venda": "2026-04-13T20:43:26Z"
    },
    {
      "cnpj": "08529008000232",
      "tipo_combustivel": 5,
      "valor_venda": 7.850320554755986,
      "data_venda": "2026-04-13T20:41:05Z"
    },
    {
      "cnpj": "01332922000169",
      "tipo_combustivel": 5,
      "valor_venda": 8.083,
      "data_venda": "2026-04-13T20:29:21Z"
    },
    {
      "cnpj": "12688818000128",
      "tipo_combustivel": 1,
      "valor_venda": 6.839945280437757,
      "data_venda": "2026-04-14T00:49:57Z"
    },
    {
      "cnpj": "04979169000196",
      "tipo_combustivel": 1,
      "valor_venda": 6.9102209944751385,
      "data_venda": "2026-04-14T02:52:14Z"
    },
    {
      "cnpj": "05885727000117",
      "tipo_combustivel": 1,
      "valor_venda": 6.928406466512702,
      "data_venda": "2026-04-13T22:43:27Z"
    },
    {
      "cnpj": "08529008000151",
      "tipo_combustivel": 1,
      "valor_venda": 6.949741503517247,
      "data_venda": "2026-04-14T01:50:20Z"
    },
    {
      "cnpj": "08529008000232",
      "tipo_combustivel": 1,
      "valor_venda": 6.950236308034473,
      "data_venda": "2026-04-12T22:09:14Z"
    },
    {
      "cnpj": "26362482000113",
      "tipo_combustivel": 1,
      "valor_venda": 6.950236308034473,
      "data_venda": "2026-04-12T11:02:58Z"
    },
    {
      "cnpj": "08418303000130",
      "tipo_combustivel": 1,
      "valor_venda": 6.9700765483646485,
      "data_venda": "2026-04-14T00:56:37Z"
    },
    {
      "cnpj": "01332922000169",
      "tipo_combustivel": 1,
      "valor_venda": 6.979094076655052,
      "data_venda": "2026-04-14T02:44:39Z"
    },
    {
      "cnpj": "05738409000123",
      "tipo_combustivel": 2,
      "valor_venda": 6.698996655518394,
      "data_venda": "2026-04-13T23:28:00Z"
    },
    {
      "cnpj": "26362482000113",
      "tipo_combustivel": 2,
      "valor_venda": 7.050197405527355,
      "data_venda": "2026-04-14T01:37:25Z"
    },
    {
      "cnpj": "08529008000151",
      "tipo_combustivel": 2,
      "valor_venda": 7.050197405527355,
      "data_venda": "2026-04-14T00:14:35Z"
    },
    {
      "cnpj": "05885727000117",
      "tipo_combustivel": 2,
      "valor_venda": 7.067137809187279,
      "data_venda": "2026-04-13T22:40:40Z"
    },
    {
      "cnpj": "08529008000232",
      "tipo_combustivel": 2,
      "valor_venda": 7.089684509039348,
      "data_venda": "2026-04-14T01:21:58Z"
    },
    {
      "cnpj": "01332922000169",
      "tipo_combustivel": 2,
      "valor_venda": 7.137758743754461,
      "data_venda": "2026-04-14T02:44:39Z"
    },
    {
      "cnpj": "08418303000130",
      "tipo_combustivel": 2,
      "valor_venda": 7.15000715000715,
      "data_venda": "2026-04-14T00:54:33Z"
    },
    {
      "cnpj": "05738409000123",
      "tipo_combustivel": 3,
      "valor_venda": 5.299901671583087,
      "data_venda": "2026-04-13T23:29:29Z"
    },
    {
      "cnpj": "12688818000128",
      "tipo_combustivel": 3,
      "valor_venda": 5.6002800140007,
      "data_venda": "2026-04-14T00:15:53Z"
    },
    {
      "cnpj": "05885727000117",
      "tipo_combustivel": 3,
      "valor_venda": 5.9297912713472485,
      "data_venda": "2026-04-13T22:35:14Z"
    },
    {
      "cnpj": "04979169000196",
      "tipo_combustivel": 3,
      "valor_venda": 5.9301775147928995,
      "data_venda": "2026-04-14T02:52:14Z"
    },
    {
      "cnpj": "08529008000232",
      "tipo_combustivel": 3,
      "valor_venda": 5.9523809523809526,
      "data_venda": "2026-04-14T00:18:49Z"
    },
    {
      "cnpj": "08418303000130",
      "tipo_combustivel": 3,
      "valor_venda": 5.958904109589041,
      "data_venda": "2026-04-13T23:57:48Z"
    },
    {
      "cnpj": "26362482000113",
      "tipo_combustivel": 3,
      "valor_venda": 5.959830740806961,
      "data_venda": "2026-04-14T01:05:52Z"
    },
    {
      "cnpj": "08529008000151",
      "tipo_combustivel": 3,
      "valor_venda": 5.960185957801883,
      "data_venda": "2026-04-14T00:15:56Z"
    },
    {
      "cnpj": "01332922000169",
      "tipo_combustivel": 3,
      "valor_venda": 5.970149253731344,
      "data_venda": "2026-04-14T02:44:39Z"
    },
    {
      "cnpj": "08529008000151",
      "tipo_combustivel": 5,
      "valor_venda": 7.150027808676307,
      "data_venda": "2026-04-14T01:32:31Z"
    },
    {
      "cnpj": "26362482000113",
      "tipo_combustivel": 5,
      "valor_venda": 7.689702939818377,
      "data_venda": "2026-04-14T01:40:59Z"
    },
    {
      "cnpj": "12688818000128",
      "tipo_combustivel": 5,
      "valor_venda": 7.8000078000078,
      "data_venda": "2026-04-14T00:15:53Z"
    },
    {
      "cnpj": "04979169000196",
      "tipo_combustivel": 5,
      "valor_venda": 7.801556420233463,
      "data_venda": "2026-04-14T02:51:57Z"
    },
    {
      "cnpj": "05885727000117",
      "tipo_combustivel": 5,
      "valor_venda": 7.830240388379924,
      "data_venda": "2026-04-13T22:41:21Z"
    },
    {
      "cnpj": "08529008000232",
      "tipo_combustivel": 5,
      "valor_venda": 7.84979702300406,
      "data_venda": "2026-04-13T21:16:52Z"
    },
    {
      "cnpj": "08529008000151",
      "tipo_combustivel": 5,
      "valor_venda": 7.849909726038151,
      "data_venda": "2026-04-13T22:32:59Z"
    },
    {
      "cnpj": "08418303000130",
      "tipo_combustivel": 5,
      "valor_venda": 7.85,
      "data_venda": "2026-04-14T00:55:18Z"
    },
    {
      "cnpj": "08529008000232",
      "tipo_combustivel": 5,
      "valor_venda": 7.850525985241011,
      "data_venda": "2026-04-14T01:14:56Z"
    },
    {
      "cnpj": "01332922000169",
      "tipo_combustivel": 5,
      "valor_venda": 8.083,
      "data_venda": "2026-04-14T01:27:36Z"
    },
    {
      "cnpj": "08529008000232",
      "tipo_combustivel": 1,
      "valor_venda": 6.95,
      "data_venda": "2026-04-14T07:22:23Z"
    },
    {
      "cnpj": "26362482000113",
      "tipo_combustivel": 1,
      "valor_venda": 6.950231481481482,
      "data_venda": "2026-04-14T07:11:34Z"
    },
    {
      "cnpj": "08529008000151",
      "tipo_combustivel": 5,
      "valor_venda": 7.150004774974152,
      "data_venda": "2026-04-14T07:35:13Z"
    }
  ]
}